<stg><name>big_mult_v3<94, 17></name>


<trans_list>

<trans id="184" from="1" to="2">
<condition id="44">
<or_exp><and_exp></and_exp></or_exp>
</condition>
</trans>

<trans id="185" from="2" to="12">
<condition id="45">
<or_exp><and_exp><literal name="exitcond3" val="1"/>
</and_exp></or_exp>
</condition>
</trans>

<trans id="186" from="2" to="3">
<condition id="47">
<or_exp><and_exp><literal name="exitcond3" val="0"/>
</and_exp></or_exp>
</condition>
</trans>

<trans id="187" from="3" to="4">
<condition id="48">
<or_exp><and_exp><literal name="exitcond5" val="0"/>
</and_exp></or_exp>
</condition>
</trans>

<trans id="197" from="3" to="2">
<condition id="60">
<or_exp><and_exp><literal name="exitcond5" val="1"/>
</and_exp></or_exp>
</condition>
</trans>

<trans id="189" from="4" to="5">
<condition id="50">
<or_exp><and_exp></and_exp></or_exp>
</condition>
</trans>

<trans id="190" from="5" to="6">
<condition id="51">
<or_exp><and_exp></and_exp></or_exp>
</condition>
</trans>

<trans id="191" from="6" to="7">
<condition id="52">
<or_exp><and_exp></and_exp></or_exp>
</condition>
</trans>

<trans id="192" from="7" to="8">
<condition id="53">
<or_exp><and_exp></and_exp></or_exp>
</condition>
</trans>

<trans id="193" from="8" to="9">
<condition id="54">
<or_exp><and_exp></and_exp></or_exp>
</condition>
</trans>

<trans id="194" from="9" to="10">
<condition id="55">
<or_exp><and_exp></and_exp></or_exp>
</condition>
</trans>

<trans id="195" from="10" to="11">
<condition id="56">
<or_exp><and_exp></and_exp></or_exp>
</condition>
</trans>

<trans id="196" from="11" to="3">
<condition id="58">
<or_exp><and_exp></and_exp></or_exp>
</condition>
</trans>

<trans id="199" from="12" to="13">
<condition id="63">
<or_exp><and_exp></and_exp></or_exp>
</condition>
</trans>

<trans id="200" from="13" to="14">
<condition id="64">
<or_exp><and_exp><literal name="exitcond4" val="0"/>
</and_exp></or_exp>
</condition>
</trans>

<trans id="207" from="13" to="17">
<condition id="75">
<or_exp><and_exp><literal name="exitcond4" val="1"/>
</and_exp></or_exp>
</condition>
</trans>

<trans id="202" from="14" to="15">
<condition id="67">
<or_exp><and_exp></and_exp></or_exp>
</condition>
</trans>

<trans id="203" from="15" to="16">
<condition id="68">
<or_exp><and_exp><literal name="exitcond6" val="0"/>
</and_exp></or_exp>
</condition>
</trans>

<trans id="206" from="15" to="13">
<condition id="73">
<or_exp><and_exp><literal name="exitcond6" val="1"/>
</and_exp></or_exp>
</condition>
</trans>

<trans id="205" from="16" to="15">
<condition id="71">
<or_exp><and_exp></and_exp></or_exp>
</condition>
</trans>

<trans id="208" from="17" to="18">
<condition id="76">
<or_exp><and_exp><literal name="exitcond" val="0"/>
</and_exp></or_exp>
</condition>
</trans>

<trans id="210" from="18" to="17">
<condition id="79">
<or_exp><and_exp></and_exp></or_exp>
</condition>
</trans>
</trans_list>



<state_list>

<state id="1" st_id="1">

<operation id="19" st_id="1" stage="1" lat="1">
<core>NULL</core>
<MemPortIdVec></MemPortIdVec>
<condition id="0">
<or_exp><and_exp></and_exp></or_exp>
</condition>

<Node id="2" bw="78" op_0_bw="78" op_1_bw="78">
<![CDATA[
.preheader163.preheader:0  %a_V_read = call i78 @_ssdm_op_Read.ap_auto.i78(i78 %a_V)

]]></Node>
<StgValue><ssdm name="a_V_read"/></StgValue>
</operation>

<operation id="20" st_id="1" stage="1" lat="1">
<core>NULL</core>
<MemPortIdVec></MemPortIdVec>
<condition id="0">
<or_exp><and_exp></and_exp></or_exp>
</condition>

<Node id="3" bw="94" op_0_bw="78">
<![CDATA[
.preheader163.preheader:1  %a_V_cast = zext i78 %a_V_read to i94

]]></Node>
<StgValue><ssdm name="a_V_cast"/></StgValue>
</operation>

<operation id="21" st_id="1" stage="1" lat="1">
<core>RAM</core>
<MemPortIdVec></MemPortIdVec>
<condition id="0">
<or_exp><and_exp></and_exp></or_exp>
</condition>

<Node id="4" bw="34" op_0_bw="64">
<![CDATA[
.preheader163.preheader:2  %pp_V = alloca [36 x i34], align 8

]]></Node>
<StgValue><ssdm name="pp_V"/><MemPortTyVec>2 3 </MemPortTyVec>
</StgValue>
</operation>

<operation id="22" st_id="1" stage="1" lat="1">
<core>NULL</core>
<MemPortIdVec></MemPortIdVec>
<condition id="0">
<or_exp><and_exp></and_exp></or_exp>
</condition>

<Node id="5" bw="6" op_0_bw="34" op_1_bw="64" op_2_bw="64">
<![CDATA[
.preheader163.preheader:3  %pp_V_addr = getelementptr [36 x i34]* %pp_V, i64 0, i64 0

]]></Node>
<StgValue><ssdm name="pp_V_addr"/></StgValue>
</operation>

<operation id="23" st_id="1" stage="1" lat="1">
<core>RAM</core>
<MemPortIdVec></MemPortIdVec>
<condition id="0">
<or_exp><and_exp></and_exp></or_exp>
</condition>

<Node id="6" bw="48" op_0_bw="64">
<![CDATA[
.preheader163.preheader:4  %pps_V = alloca [12 x i48], align 8

]]></Node>
<StgValue><ssdm name="pps_V"/><MemPortTyVec>2 3 </MemPortTyVec>
</StgValue>
</operation>

<operation id="24" st_id="1" stage="1" lat="1">
<core>NULL</core>
<MemPortIdVec></MemPortIdVec>
<condition id="0">
<or_exp><and_exp></and_exp></or_exp>
</condition>

<Node id="7" bw="0" op_0_bw="0">
<![CDATA[
.preheader163.preheader:5  br label %.preheader163

]]></Node>
<StgValue><ssdm name=""/></StgValue>
</operation>
</state>

<state id="2" st_id="2">

<operation id="25" st_id="2" stage="1" lat="1">
<core>NULL</core>
<MemPortIdVec></MemPortIdVec>
<condition id="1">
<or_exp><and_exp></and_exp></or_exp>
</condition>

<Node id="9" bw="3" op_0_bw="3" op_1_bw="0">
<![CDATA[
.preheader163:0  %i = phi i3 [ 0, %.preheader163.preheader ], [ %i_11, %.preheader163.loopexit ]

]]></Node>
<StgValue><ssdm name="i"/></StgValue>
</operation>

<operation id="26" st_id="2" stage="1" lat="1">
<core>Cmp</core>
<MemPortIdVec></MemPortIdVec>
<condition id="1">
<or_exp><and_exp></and_exp></or_exp>
</condition>

<Node id="10" bw="1" op_0_bw="3" op_1_bw="3">
<![CDATA[
.preheader163:1  %exitcond3 = icmp eq i3 %i, -2

]]></Node>
<StgValue><ssdm name="exitcond3"/></StgValue>
</operation>

<operation id="27" st_id="2" stage="1" lat="1">
<core>NULL</core>
<MemPortIdVec></MemPortIdVec>
<condition id="1">
<or_exp><and_exp></and_exp></or_exp>
</condition>

<Node id="11" bw="32" op_0_bw="32" op_1_bw="64" op_2_bw="64" op_3_bw="64">
<![CDATA[
.preheader163:2  %empty = call i32 (...)* @_ssdm_op_SpecLoopTripCount(i64 6, i64 6, i64 6)

]]></Node>
<StgValue><ssdm name="empty"/></StgValue>
</operation>

<operation id="28" st_id="2" stage="1" lat="1">
<core>AddSub</core>
<MemPortIdVec></MemPortIdVec>
<condition id="1">
<or_exp><and_exp></and_exp></or_exp>
</condition>

<Node id="12" bw="3" op_0_bw="3" op_1_bw="3">
<![CDATA[
.preheader163:3  %i_11 = add i3 %i, 1

]]></Node>
<StgValue><ssdm name="i_11"/></StgValue>
</operation>

<operation id="29" st_id="2" stage="1" lat="1">
<core>NULL</core>
<MemPortIdVec></MemPortIdVec>
<condition id="1">
<or_exp><and_exp></and_exp></or_exp>
</condition>

<Node id="13" bw="0" op_0_bw="1" op_1_bw="0" op_2_bw="0">
<![CDATA[
.preheader163:4  br i1 %exitcond3, label %arrayctor.loop4.preheader, label %.preheader162.preheader

]]></Node>
<StgValue><ssdm name=""/></StgValue>
</operation>

<operation id="30" st_id="2" stage="1" lat="1">
<core>Cmp</core>
<MemPortIdVec></MemPortIdVec>
<condition id="3">
<or_exp><and_exp><literal name="exitcond3" val="0"/>
</and_exp></or_exp>
</condition>

<Node id="15" bw="1" op_0_bw="3" op_1_bw="3">
<![CDATA[
.preheader162.preheader:0  %tmp_s = icmp eq i3 %i, -3

]]></Node>
<StgValue><ssdm name="tmp_s"/></StgValue>
</operation>

<operation id="31" st_id="2" stage="1" lat="1">
<core>NULL</core>
<MemPortIdVec></MemPortIdVec>
<condition id="3">
<or_exp><and_exp><literal name="exitcond3" val="0"/>
</and_exp></or_exp>
</condition>

<Node id="16" bw="6" op_0_bw="6" op_1_bw="3" op_2_bw="3">
<![CDATA[
.preheader162.preheader:1  %tmp_290 = call i6 @_ssdm_op_BitConcatenate.i6.i3.i3(i3 %i, i3 0)

]]></Node>
<StgValue><ssdm name="tmp_290"/></StgValue>
</operation>

<operation id="32" st_id="2" stage="1" lat="1">
<core>NULL</core>
<MemPortIdVec></MemPortIdVec>
<condition id="3">
<or_exp><and_exp><literal name="exitcond3" val="0"/>
</and_exp></or_exp>
</condition>

<Node id="17" bw="7" op_0_bw="6">
<![CDATA[
.preheader162.preheader:2  %p_shl_cast = zext i6 %tmp_290 to i7

]]></Node>
<StgValue><ssdm name="p_shl_cast"/></StgValue>
</operation>

<operation id="33" st_id="2" stage="1" lat="1">
<core>NULL</core>
<MemPortIdVec></MemPortIdVec>
<condition id="3">
<or_exp><and_exp><literal name="exitcond3" val="0"/>
</and_exp></or_exp>
</condition>

<Node id="18" bw="4" op_0_bw="4" op_1_bw="3" op_2_bw="1">
<![CDATA[
.preheader162.preheader:3  %tmp_291 = call i4 @_ssdm_op_BitConcatenate.i4.i3.i1(i3 %i, i1 false)

]]></Node>
<StgValue><ssdm name="tmp_291"/></StgValue>
</operation>

<operation id="34" st_id="2" stage="1" lat="1">
<core>NULL</core>
<MemPortIdVec></MemPortIdVec>
<condition id="3">
<or_exp><and_exp><literal name="exitcond3" val="0"/>
</and_exp></or_exp>
</condition>

<Node id="19" bw="7" op_0_bw="4">
<![CDATA[
.preheader162.preheader:4  %p_shl1_cast = zext i4 %tmp_291 to i7

]]></Node>
<StgValue><ssdm name="p_shl1_cast"/></StgValue>
</operation>

<operation id="35" st_id="2" stage="1" lat="1">
<core>AddSub</core>
<MemPortIdVec></MemPortIdVec>
<condition id="3">
<or_exp><and_exp><literal name="exitcond3" val="0"/>
</and_exp></or_exp>
</condition>

<Node id="20" bw="7" op_0_bw="7" op_1_bw="7">
<![CDATA[
.preheader162.preheader:5  %tmp_292 = sub i7 %p_shl_cast, %p_shl1_cast

]]></Node>
<StgValue><ssdm name="tmp_292"/></StgValue>
</operation>

<operation id="36" st_id="2" stage="1" lat="1">
<core>NULL</core>
<MemPortIdVec></MemPortIdVec>
<condition id="3">
<or_exp><and_exp><literal name="exitcond3" val="0"/>
</and_exp></or_exp>
</condition>

<Node id="21" bw="7" op_0_bw="7" op_1_bw="3" op_2_bw="1" op_3_bw="3">
<![CDATA[
.preheader162.preheader:6  %Lo_assign = call i7 @_ssdm_op_BitConcatenate.i7.i3.i1.i3(i3 %i, i1 false, i3 %i)

]]></Node>
<StgValue><ssdm name="Lo_assign"/></StgValue>
</operation>

<operation id="37" st_id="2" stage="1" lat="1">
<core>AddSub</core>
<MemPortIdVec></MemPortIdVec>
<condition id="3">
<or_exp><and_exp><literal name="exitcond3" val="0"/>
</and_exp></or_exp>
</condition>

<Node id="22" bw="7" op_0_bw="7" op_1_bw="7">
<![CDATA[
.preheader162.preheader:7  %tmp_183 = add i7 %Lo_assign, 16

]]></Node>
<StgValue><ssdm name="tmp_183"/></StgValue>
</operation>

<operation id="38" st_id="2" stage="1" lat="1">
<core>Sel</core>
<MemPortIdVec></MemPortIdVec>
<condition id="3">
<or_exp><and_exp><literal name="exitcond3" val="0"/>
</and_exp></or_exp>
</condition>

<Node id="23" bw="7" op_0_bw="1" op_1_bw="7" op_2_bw="7">
<![CDATA[
.preheader162.preheader:8  %Ui_2 = select i1 %tmp_s, i7 -35, i7 %tmp_183

]]></Node>
<StgValue><ssdm name="Ui_2"/></StgValue>
</operation>

<operation id="39" st_id="2" stage="1" lat="1">
<core>NULL</core>
<MemPortIdVec></MemPortIdVec>
<condition id="3">
<or_exp><and_exp><literal name="exitcond3" val="0"/>
</and_exp></or_exp>
</condition>

<Node id="24" bw="0" op_0_bw="0">
<![CDATA[
.preheader162.preheader:9  br label %.preheader162

]]></Node>
<StgValue><ssdm name=""/></StgValue>
</operation>

<operation id="40" st_id="2" stage="2" lat="2">
<core>RAM</core>
<MemPortIdVec>0 </MemPortIdVec>
<condition id="5">
<or_exp><and_exp><literal name="exitcond3" val="1"/>
</and_exp></or_exp>
</condition>

<Node id="75" bw="34" op_0_bw="6">
<![CDATA[
arrayctor.loop4.preheader:0  %pp_V_load = load i34* %pp_V_addr, align 16

]]></Node>
<StgValue><ssdm name="pp_V_load"/></StgValue>
</operation>
</state>

<state id="3" st_id="3">

<operation id="41" st_id="3" stage="1" lat="1">
<core>NULL</core>
<MemPortIdVec></MemPortIdVec>
<condition id="6">
<or_exp><and_exp></and_exp></or_exp>
</condition>

<Node id="26" bw="3" op_0_bw="3" op_1_bw="0">
<![CDATA[
.preheader162:0  %j = phi i3 [ %j_6, %_ifconv ], [ 0, %.preheader162.preheader ]

]]></Node>
<StgValue><ssdm name="j"/></StgValue>
</operation>

<operation id="42" st_id="3" stage="1" lat="1">
<core>Cmp</core>
<MemPortIdVec></MemPortIdVec>
<condition id="6">
<or_exp><and_exp></and_exp></or_exp>
</condition>

<Node id="27" bw="1" op_0_bw="3" op_1_bw="3">
<![CDATA[
.preheader162:1  %exitcond5 = icmp eq i3 %j, -2

]]></Node>
<StgValue><ssdm name="exitcond5"/></StgValue>
</operation>

<operation id="43" st_id="3" stage="1" lat="1">
<core>NULL</core>
<MemPortIdVec></MemPortIdVec>
<condition id="6">
<or_exp><and_exp></and_exp></or_exp>
</condition>

<Node id="28" bw="32" op_0_bw="32" op_1_bw="64" op_2_bw="64" op_3_bw="64">
<![CDATA[
.preheader162:2  %empty_59 = call i32 (...)* @_ssdm_op_SpecLoopTripCount(i64 6, i64 6, i64 6)

]]></Node>
<StgValue><ssdm name="empty_59"/></StgValue>
</operation>

<operation id="44" st_id="3" stage="1" lat="1">
<core>AddSub</core>
<MemPortIdVec></MemPortIdVec>
<condition id="6">
<or_exp><and_exp></and_exp></or_exp>
</condition>

<Node id="29" bw="3" op_0_bw="3" op_1_bw="3">
<![CDATA[
.preheader162:3  %j_6 = add i3 %j, 1

]]></Node>
<StgValue><ssdm name="j_6"/></StgValue>
</operation>

<operation id="45" st_id="3" stage="1" lat="1">
<core>NULL</core>
<MemPortIdVec></MemPortIdVec>
<condition id="6">
<or_exp><and_exp></and_exp></or_exp>
</condition>

<Node id="30" bw="0" op_0_bw="1" op_1_bw="0" op_2_bw="0">
<![CDATA[
.preheader162:4  br i1 %exitcond5, label %.preheader163.loopexit, label %_ifconv

]]></Node>
<StgValue><ssdm name=""/></StgValue>
</operation>

<operation id="46" st_id="3" stage="1" lat="1">
<core>Cmp</core>
<MemPortIdVec></MemPortIdVec>
<condition id="8">
<or_exp><and_exp><literal name="exitcond5" val="0"/>
</and_exp></or_exp>
</condition>

<Node id="32" bw="1" op_0_bw="3" op_1_bw="3">
<![CDATA[
_ifconv:0  %tmp_187 = icmp eq i3 %j, -3

]]></Node>
<StgValue><ssdm name="tmp_187"/></StgValue>
</operation>

<operation id="47" st_id="3" stage="1" lat="1">
<core>NULL</core>
<MemPortIdVec></MemPortIdVec>
<condition id="8">
<or_exp><and_exp><literal name="exitcond5" val="0"/>
</and_exp></or_exp>
</condition>

<Node id="33" bw="7" op_0_bw="7" op_1_bw="3" op_2_bw="1" op_3_bw="3">
<![CDATA[
_ifconv:1  %Lo_assign_1 = call i7 @_ssdm_op_BitConcatenate.i7.i3.i1.i3(i3 %j, i1 false, i3 %j)

]]></Node>
<StgValue><ssdm name="Lo_assign_1"/></StgValue>
</operation>

<operation id="48" st_id="3" stage="1" lat="1">
<core>AddSub</core>
<MemPortIdVec></MemPortIdVec>
<condition id="8">
<or_exp><and_exp><literal name="exitcond5" val="0"/>
</and_exp></or_exp>
</condition>

<Node id="34" bw="7" op_0_bw="7" op_1_bw="7">
<![CDATA[
_ifconv:2  %tmp_188 = add i7 16, %Lo_assign_1

]]></Node>
<StgValue><ssdm name="tmp_188"/></StgValue>
</operation>

<operation id="49" st_id="3" stage="1" lat="1">
<core>Sel</core>
<MemPortIdVec></MemPortIdVec>
<condition id="8">
<or_exp><and_exp><literal name="exitcond5" val="0"/>
</and_exp></or_exp>
</condition>

<Node id="35" bw="7" op_0_bw="1" op_1_bw="7" op_2_bw="7">
<![CDATA[
_ifconv:3  %Uj = select i1 %tmp_187, i7 -35, i7 %tmp_188

]]></Node>
<StgValue><ssdm name="Uj"/></StgValue>
</operation>

<operation id="50" st_id="3" stage="1" lat="1">
<core>NULL</core>
<MemPortIdVec></MemPortIdVec>
<condition id="8">
<or_exp><and_exp><literal name="exitcond5" val="0"/>
</and_exp></or_exp>
</condition>

<Node id="36" bw="7" op_0_bw="3">
<![CDATA[
_ifconv:4  %tmp_189_cast = zext i3 %j to i7

]]></Node>
<StgValue><ssdm name="tmp_189_cast"/></StgValue>
</operation>

<operation id="51" st_id="3" stage="1" lat="1">
<core>AddSub</core>
<MemPortIdVec></MemPortIdVec>
<condition id="8">
<or_exp><and_exp><literal name="exitcond5" val="0"/>
</and_exp></or_exp>
</condition>

<Node id="37" bw="7" op_0_bw="7" op_1_bw="7">
<![CDATA[
_ifconv:5  %tmp_293 = add i7 %tmp_292, %tmp_189_cast

]]></Node>
<StgValue><ssdm name="tmp_293"/></StgValue>
</operation>

<operation id="52" st_id="3" stage="1" lat="1">
<core>Cmp</core>
<MemPortIdVec></MemPortIdVec>
<condition id="8">
<or_exp><and_exp><literal name="exitcond5" val="0"/>
</and_exp></or_exp>
</condition>

<Node id="40" bw="1" op_0_bw="7" op_1_bw="7">
<![CDATA[
_ifconv:8  %tmp_358 = icmp ugt i7 %Lo_assign, %Ui_2

]]></Node>
<StgValue><ssdm name="tmp_358"/></StgValue>
</operation>

<operation id="53" st_id="3" stage="1" lat="1">
<core>NULL</core>
<MemPortIdVec></MemPortIdVec>
<condition id="8">
<or_exp><and_exp><literal name="exitcond5" val="0"/>
</and_exp></or_exp>
</condition>

<Node id="41" bw="94" op_0_bw="94" op_1_bw="94" op_2_bw="32" op_3_bw="32">
<![CDATA[
_ifconv:9  %tmp_359 = call i94 @llvm.part.select.i94(i94 %a_V_cast, i32 93, i32 0)

]]></Node>
<StgValue><ssdm name="tmp_359"/></StgValue>
</operation>

<operation id="54" st_id="3" stage="1" lat="1">
<core>AddSub</core>
<MemPortIdVec></MemPortIdVec>
<condition id="8">
<or_exp><and_exp><literal name="exitcond5" val="0"/>
</and_exp></or_exp>
</condition>

<Node id="42" bw="7" op_0_bw="7" op_1_bw="7">
<![CDATA[
_ifconv:10  %tmp_360 = sub i7 %Lo_assign, %Ui_2

]]></Node>
<StgValue><ssdm name="tmp_360"/></StgValue>
</operation>

<operation id="55" st_id="3" stage="1" lat="1">
<core>AddSub</core>
<MemPortIdVec></MemPortIdVec>
<condition id="8">
<or_exp><and_exp><literal name="exitcond5" val="0"/>
</and_exp></or_exp>
</condition>

<Node id="43" bw="7" op_0_bw="7" op_1_bw="7">
<![CDATA[
_ifconv:11  %tmp_361 = sub i7 -35, %Lo_assign

]]></Node>
<StgValue><ssdm name="tmp_361"/></StgValue>
</operation>

<operation id="56" st_id="3" stage="1" lat="1">
<core>AddSub</core>
<MemPortIdVec></MemPortIdVec>
<condition id="8">
<or_exp><and_exp><literal name="exitcond5" val="0"/>
</and_exp></or_exp>
</condition>

<Node id="44" bw="7" op_0_bw="7" op_1_bw="7">
<![CDATA[
_ifconv:12  %tmp_362 = sub i7 %Ui_2, %Lo_assign

]]></Node>
<StgValue><ssdm name="tmp_362"/></StgValue>
</operation>

<operation id="57" st_id="3" stage="1" lat="1">
<core>Sel</core>
<MemPortIdVec></MemPortIdVec>
<condition id="8">
<or_exp><and_exp><literal name="exitcond5" val="0"/>
</and_exp></or_exp>
</condition>

<Node id="45" bw="7" op_0_bw="1" op_1_bw="7" op_2_bw="7">
<![CDATA[
_ifconv:13  %tmp_363 = select i1 %tmp_358, i7 %tmp_360, i7 %tmp_362

]]></Node>
<StgValue><ssdm name="tmp_363"/></StgValue>
</operation>

<operation id="58" st_id="3" stage="1" lat="1">
<core>Sel</core>
<MemPortIdVec></MemPortIdVec>
<condition id="8">
<or_exp><and_exp><literal name="exitcond5" val="0"/>
</and_exp></or_exp>
</condition>

<Node id="46" bw="94" op_0_bw="1" op_1_bw="94" op_2_bw="94">
<![CDATA[
_ifconv:14  %tmp_364 = select i1 %tmp_358, i94 %tmp_359, i94 %a_V_cast

]]></Node>
<StgValue><ssdm name="tmp_364"/></StgValue>
</operation>

<operation id="59" st_id="3" stage="1" lat="1">
<core>Sel</core>
<MemPortIdVec></MemPortIdVec>
<condition id="8">
<or_exp><and_exp><literal name="exitcond5" val="0"/>
</and_exp></or_exp>
</condition>

<Node id="47" bw="7" op_0_bw="1" op_1_bw="7" op_2_bw="7">
<![CDATA[
_ifconv:15  %tmp_365 = select i1 %tmp_358, i7 %tmp_361, i7 %Lo_assign

]]></Node>
<StgValue><ssdm name="tmp_365"/></StgValue>
</operation>

<operation id="60" st_id="3" stage="1" lat="1">
<core>AddSub</core>
<MemPortIdVec></MemPortIdVec>
<condition id="8">
<or_exp><and_exp><literal name="exitcond5" val="0"/>
</and_exp></or_exp>
</condition>

<Node id="48" bw="7" op_0_bw="7" op_1_bw="7">
<![CDATA[
_ifconv:16  %tmp_366 = sub i7 -35, %tmp_363

]]></Node>
<StgValue><ssdm name="tmp_366"/></StgValue>
</operation>

<operation id="61" st_id="3" stage="1" lat="1">
<core>NULL</core>
<MemPortIdVec></MemPortIdVec>
<condition id="8">
<or_exp><and_exp><literal name="exitcond5" val="0"/>
</and_exp></or_exp>
</condition>

<Node id="49" bw="94" op_0_bw="7">
<![CDATA[
_ifconv:17  %tmp_367 = zext i7 %tmp_365 to i94

]]></Node>
<StgValue><ssdm name="tmp_367"/></StgValue>
</operation>

<operation id="62" st_id="3" stage="1" lat="1">
<core>NULL</core>
<MemPortIdVec></MemPortIdVec>
<condition id="8">
<or_exp><and_exp><literal name="exitcond5" val="0"/>
</and_exp></or_exp>
</condition>

<Node id="50" bw="94" op_0_bw="7">
<![CDATA[
_ifconv:18  %tmp_368 = zext i7 %tmp_366 to i94

]]></Node>
<StgValue><ssdm name="tmp_368"/></StgValue>
</operation>

<operation id="63" st_id="3" stage="1" lat="1">
<core>Shift</core>
<MemPortIdVec></MemPortIdVec>
<condition id="8">
<or_exp><and_exp><literal name="exitcond5" val="0"/>
</and_exp></or_exp>
</condition>

<Node id="51" bw="94" op_0_bw="94" op_1_bw="94">
<![CDATA[
_ifconv:19  %tmp_369 = lshr i94 %tmp_364, %tmp_367

]]></Node>
<StgValue><ssdm name="tmp_369"/></StgValue>
</operation>

<operation id="64" st_id="3" stage="1" lat="1">
<core>Shift</core>
<MemPortIdVec></MemPortIdVec>
<condition id="8">
<or_exp><and_exp><literal name="exitcond5" val="0"/>
</and_exp></or_exp>
</condition>

<Node id="52" bw="94" op_0_bw="94" op_1_bw="94">
<![CDATA[
_ifconv:20  %tmp_370 = lshr i94 -1, %tmp_368

]]></Node>
<StgValue><ssdm name="tmp_370"/></StgValue>
</operation>

<operation id="65" st_id="3" stage="1" lat="1">
<core>LogicGate</core>
<MemPortIdVec></MemPortIdVec>
<condition id="8">
<or_exp><and_exp><literal name="exitcond5" val="0"/>
</and_exp></or_exp>
</condition>

<Node id="53" bw="94" op_0_bw="94" op_1_bw="94">
<![CDATA[
_ifconv:21  %p_Result_16 = and i94 %tmp_369, %tmp_370

]]></Node>
<StgValue><ssdm name="p_Result_16"/></StgValue>
</operation>

<operation id="66" st_id="3" stage="1" lat="1">
<core>NULL</core>
<MemPortIdVec></MemPortIdVec>
<condition id="8">
<or_exp><and_exp><literal name="exitcond5" val="0"/>
</and_exp></or_exp>
</condition>

<Node id="67" bw="34" op_0_bw="94">
<![CDATA[
_ifconv:35  %tmp_385 = trunc i94 %p_Result_16 to i34

]]></Node>
<StgValue><ssdm name="tmp_385"/></StgValue>
</operation>

<operation id="67" st_id="3" stage="1" lat="1">
<core>NULL</core>
<MemPortIdVec></MemPortIdVec>
<condition id="10">
<or_exp><and_exp><literal name="exitcond5" val="1"/>
</and_exp></or_exp>
</condition>

<Node id="73" bw="0" op_0_bw="0">
<![CDATA[
.preheader163.loopexit:0  br label %.preheader163

]]></Node>
<StgValue><ssdm name=""/></StgValue>
</operation>
</state>

<state id="4" st_id="4">

<operation id="68" st_id="4" stage="1" lat="1">
<core>Cmp</core>
<MemPortIdVec></MemPortIdVec>
<condition id="11">
<or_exp><and_exp></and_exp></or_exp>
</condition>

<Node id="54" bw="1" op_0_bw="7" op_1_bw="7">
<![CDATA[
_ifconv:22  %tmp_372 = icmp ugt i7 %Lo_assign_1, %Uj

]]></Node>
<StgValue><ssdm name="tmp_372"/></StgValue>
</operation>

<operation id="69" st_id="4" stage="1" lat="1">
<core>AddSub</core>
<MemPortIdVec></MemPortIdVec>
<condition id="11">
<or_exp><and_exp></and_exp></or_exp>
</condition>

<Node id="55" bw="7" op_0_bw="7" op_1_bw="7">
<![CDATA[
_ifconv:23  %tmp_373 = sub i7 %Lo_assign_1, %Uj

]]></Node>
<StgValue><ssdm name="tmp_373"/></StgValue>
</operation>

<operation id="70" st_id="4" stage="1" lat="1">
<core>AddSub</core>
<MemPortIdVec></MemPortIdVec>
<condition id="11">
<or_exp><and_exp></and_exp></or_exp>
</condition>

<Node id="56" bw="7" op_0_bw="7" op_1_bw="7">
<![CDATA[
_ifconv:24  %tmp_374 = sub i7 -35, %Lo_assign_1

]]></Node>
<StgValue><ssdm name="tmp_374"/></StgValue>
</operation>

<operation id="71" st_id="4" stage="1" lat="1">
<core>AddSub</core>
<MemPortIdVec></MemPortIdVec>
<condition id="11">
<or_exp><and_exp></and_exp></or_exp>
</condition>

<Node id="57" bw="7" op_0_bw="7" op_1_bw="7">
<![CDATA[
_ifconv:25  %tmp_375 = sub i7 %Uj, %Lo_assign_1

]]></Node>
<StgValue><ssdm name="tmp_375"/></StgValue>
</operation>

<operation id="72" st_id="4" stage="1" lat="1">
<core>Sel</core>
<MemPortIdVec></MemPortIdVec>
<condition id="11">
<or_exp><and_exp></and_exp></or_exp>
</condition>

<Node id="58" bw="7" op_0_bw="1" op_1_bw="7" op_2_bw="7">
<![CDATA[
_ifconv:26  %tmp_376 = select i1 %tmp_372, i7 %tmp_373, i7 %tmp_375

]]></Node>
<StgValue><ssdm name="tmp_376"/></StgValue>
</operation>

<operation id="73" st_id="4" stage="1" lat="1">
<core>Sel</core>
<MemPortIdVec></MemPortIdVec>
<condition id="11">
<or_exp><and_exp></and_exp></or_exp>
</condition>

<Node id="59" bw="94" op_0_bw="1" op_1_bw="94" op_2_bw="94">
<![CDATA[
_ifconv:27  %tmp_377 = select i1 %tmp_372, i94 -8932543859452897742033846272, i94 237372029602271161299249

]]></Node>
<StgValue><ssdm name="tmp_377"/></StgValue>
</operation>

<operation id="74" st_id="4" stage="1" lat="1">
<core>Sel</core>
<MemPortIdVec></MemPortIdVec>
<condition id="11">
<or_exp><and_exp></and_exp></or_exp>
</condition>

<Node id="60" bw="7" op_0_bw="1" op_1_bw="7" op_2_bw="7">
<![CDATA[
_ifconv:28  %tmp_378 = select i1 %tmp_372, i7 %tmp_374, i7 %Lo_assign_1

]]></Node>
<StgValue><ssdm name="tmp_378"/></StgValue>
</operation>

<operation id="75" st_id="4" stage="1" lat="1">
<core>AddSub</core>
<MemPortIdVec></MemPortIdVec>
<condition id="11">
<or_exp><and_exp></and_exp></or_exp>
</condition>

<Node id="61" bw="7" op_0_bw="7" op_1_bw="7">
<![CDATA[
_ifconv:29  %tmp_379 = sub i7 -35, %tmp_376

]]></Node>
<StgValue><ssdm name="tmp_379"/></StgValue>
</operation>

<operation id="76" st_id="4" stage="1" lat="1">
<core>NULL</core>
<MemPortIdVec></MemPortIdVec>
<condition id="11">
<or_exp><and_exp></and_exp></or_exp>
</condition>

<Node id="62" bw="94" op_0_bw="7">
<![CDATA[
_ifconv:30  %tmp_380 = zext i7 %tmp_378 to i94

]]></Node>
<StgValue><ssdm name="tmp_380"/></StgValue>
</operation>

<operation id="77" st_id="4" stage="1" lat="1">
<core>NULL</core>
<MemPortIdVec></MemPortIdVec>
<condition id="11">
<or_exp><and_exp></and_exp></or_exp>
</condition>

<Node id="63" bw="94" op_0_bw="7">
<![CDATA[
_ifconv:31  %tmp_381 = zext i7 %tmp_379 to i94

]]></Node>
<StgValue><ssdm name="tmp_381"/></StgValue>
</operation>

<operation id="78" st_id="4" stage="1" lat="1">
<core>Shift</core>
<MemPortIdVec></MemPortIdVec>
<condition id="11">
<or_exp><and_exp></and_exp></or_exp>
</condition>

<Node id="64" bw="94" op_0_bw="94" op_1_bw="94">
<![CDATA[
_ifconv:32  %tmp_382 = lshr i94 %tmp_377, %tmp_380

]]></Node>
<StgValue><ssdm name="tmp_382"/></StgValue>
</operation>

<operation id="79" st_id="4" stage="1" lat="1">
<core>Shift</core>
<MemPortIdVec></MemPortIdVec>
<condition id="11">
<or_exp><and_exp></and_exp></or_exp>
</condition>

<Node id="65" bw="94" op_0_bw="94" op_1_bw="94">
<![CDATA[
_ifconv:33  %tmp_383 = lshr i94 -1, %tmp_381

]]></Node>
<StgValue><ssdm name="tmp_383"/></StgValue>
</operation>

<operation id="80" st_id="4" stage="1" lat="1">
<core>LogicGate</core>
<MemPortIdVec></MemPortIdVec>
<condition id="11">
<or_exp><and_exp></and_exp></or_exp>
</condition>

<Node id="66" bw="94" op_0_bw="94" op_1_bw="94">
<![CDATA[
_ifconv:34  %p_Result_17 = and i94 %tmp_382, %tmp_383

]]></Node>
<StgValue><ssdm name="p_Result_17"/></StgValue>
</operation>

<operation id="81" st_id="4" stage="1" lat="1">
<core>NULL</core>
<MemPortIdVec></MemPortIdVec>
<condition id="11">
<or_exp><and_exp></and_exp></or_exp>
</condition>

<Node id="68" bw="34" op_0_bw="94">
<![CDATA[
_ifconv:36  %tmp_386 = trunc i94 %p_Result_17 to i34

]]></Node>
<StgValue><ssdm name="tmp_386"/></StgValue>
</operation>
</state>

<state id="5" st_id="5">

<operation id="82" st_id="5" stage="6" lat="6">
<core>MulnS</core>
<MemPortIdVec></MemPortIdVec>
<condition id="12">
<or_exp><and_exp></and_exp></or_exp>
</condition>

<Node id="69" bw="34" op_0_bw="34" op_1_bw="34">
<![CDATA[
_ifconv:37  %tmp_192 = mul i34 %tmp_386, %tmp_385

]]></Node>
<StgValue><ssdm name="tmp_192"/></StgValue>
</operation>
</state>

<state id="6" st_id="6">

<operation id="83" st_id="6" stage="5" lat="6">
<core>MulnS</core>
<MemPortIdVec></MemPortIdVec>
<condition id="13">
<or_exp><and_exp></and_exp></or_exp>
</condition>

<Node id="69" bw="34" op_0_bw="34" op_1_bw="34">
<![CDATA[
_ifconv:37  %tmp_192 = mul i34 %tmp_386, %tmp_385

]]></Node>
<StgValue><ssdm name="tmp_192"/></StgValue>
</operation>
</state>

<state id="7" st_id="7">

<operation id="84" st_id="7" stage="4" lat="6">
<core>MulnS</core>
<MemPortIdVec></MemPortIdVec>
<condition id="14">
<or_exp><and_exp></and_exp></or_exp>
</condition>

<Node id="69" bw="34" op_0_bw="34" op_1_bw="34">
<![CDATA[
_ifconv:37  %tmp_192 = mul i34 %tmp_386, %tmp_385

]]></Node>
<StgValue><ssdm name="tmp_192"/></StgValue>
</operation>
</state>

<state id="8" st_id="8">

<operation id="85" st_id="8" stage="3" lat="6">
<core>MulnS</core>
<MemPortIdVec></MemPortIdVec>
<condition id="15">
<or_exp><and_exp></and_exp></or_exp>
</condition>

<Node id="69" bw="34" op_0_bw="34" op_1_bw="34">
<![CDATA[
_ifconv:37  %tmp_192 = mul i34 %tmp_386, %tmp_385

]]></Node>
<StgValue><ssdm name="tmp_192"/></StgValue>
</operation>
</state>

<state id="9" st_id="9">

<operation id="86" st_id="9" stage="2" lat="6">
<core>MulnS</core>
<MemPortIdVec></MemPortIdVec>
<condition id="16">
<or_exp><and_exp></and_exp></or_exp>
</condition>

<Node id="69" bw="34" op_0_bw="34" op_1_bw="34">
<![CDATA[
_ifconv:37  %tmp_192 = mul i34 %tmp_386, %tmp_385

]]></Node>
<StgValue><ssdm name="tmp_192"/></StgValue>
</operation>
</state>

<state id="10" st_id="10">

<operation id="87" st_id="10" stage="1" lat="6">
<core>MulnS</core>
<MemPortIdVec></MemPortIdVec>
<condition id="17">
<or_exp><and_exp></and_exp></or_exp>
</condition>

<Node id="69" bw="34" op_0_bw="34" op_1_bw="34">
<![CDATA[
_ifconv:37  %tmp_192 = mul i34 %tmp_386, %tmp_385

]]></Node>
<StgValue><ssdm name="tmp_192"/></StgValue>
</operation>
</state>

<state id="11" st_id="11">

<operation id="88" st_id="11" stage="1" lat="1">
<core>NULL</core>
<MemPortIdVec></MemPortIdVec>
<condition id="18">
<or_exp><and_exp></and_exp></or_exp>
</condition>

<Node id="38" bw="64" op_0_bw="7">
<![CDATA[
_ifconv:6  %tmp_299_cast = sext i7 %tmp_293 to i64

]]></Node>
<StgValue><ssdm name="tmp_299_cast"/></StgValue>
</operation>

<operation id="89" st_id="11" stage="1" lat="1">
<core>NULL</core>
<MemPortIdVec></MemPortIdVec>
<condition id="18">
<or_exp><and_exp></and_exp></or_exp>
</condition>

<Node id="39" bw="6" op_0_bw="34" op_1_bw="64" op_2_bw="64">
<![CDATA[
_ifconv:7  %pp_V_addr_3 = getelementptr [36 x i34]* %pp_V, i64 0, i64 %tmp_299_cast

]]></Node>
<StgValue><ssdm name="pp_V_addr_3"/></StgValue>
</operation>

<operation id="90" st_id="11" stage="1" lat="1">
<core>RAM</core>
<MemPortIdVec>0 </MemPortIdVec>
<condition id="18">
<or_exp><and_exp></and_exp></or_exp>
</condition>

<Node id="70" bw="0" op_0_bw="34" op_1_bw="6">
<![CDATA[
_ifconv:38  store i34 %tmp_192, i34* %pp_V_addr_3, align 8

]]></Node>
<StgValue><ssdm name=""/></StgValue>
</operation>

<operation id="91" st_id="11" stage="1" lat="1">
<core>NULL</core>
<MemPortIdVec></MemPortIdVec>
<condition id="18">
<or_exp><and_exp></and_exp></or_exp>
</condition>

<Node id="71" bw="0" op_0_bw="0">
<![CDATA[
_ifconv:39  br label %.preheader162

]]></Node>
<StgValue><ssdm name=""/></StgValue>
</operation>
</state>

<state id="12" st_id="12">

<operation id="92" st_id="12" stage="1" lat="2">
<core>RAM</core>
<MemPortIdVec>0 </MemPortIdVec>
<condition id="19">
<or_exp><and_exp></and_exp></or_exp>
</condition>

<Node id="75" bw="34" op_0_bw="6">
<![CDATA[
arrayctor.loop4.preheader:0  %pp_V_load = load i34* %pp_V_addr, align 16

]]></Node>
<StgValue><ssdm name="pp_V_load"/></StgValue>
</operation>

<operation id="93" st_id="12" stage="1" lat="1">
<core>NULL</core>
<MemPortIdVec></MemPortIdVec>
<condition id="19">
<or_exp><and_exp></and_exp></or_exp>
</condition>

<Node id="76" bw="48" op_0_bw="34">
<![CDATA[
arrayctor.loop4.preheader:1  %tmp = zext i34 %pp_V_load to i48

]]></Node>
<StgValue><ssdm name="tmp"/></StgValue>
</operation>

<operation id="94" st_id="12" stage="1" lat="1">
<core>NULL</core>
<MemPortIdVec></MemPortIdVec>
<condition id="19">
<or_exp><and_exp></and_exp></or_exp>
</condition>

<Node id="77" bw="4" op_0_bw="48" op_1_bw="64" op_2_bw="64">
<![CDATA[
arrayctor.loop4.preheader:2  %pps_V_addr = getelementptr [12 x i48]* %pps_V, i64 0, i64 0

]]></Node>
<StgValue><ssdm name="pps_V_addr"/></StgValue>
</operation>

<operation id="95" st_id="12" stage="1" lat="1">
<core>RAM</core>
<MemPortIdVec>0 </MemPortIdVec>
<condition id="19">
<or_exp><and_exp></and_exp></or_exp>
</condition>

<Node id="78" bw="0" op_0_bw="48" op_1_bw="4">
<![CDATA[
arrayctor.loop4.preheader:3  store i48 %tmp, i48* %pps_V_addr, align 16

]]></Node>
<StgValue><ssdm name=""/></StgValue>
</operation>

<operation id="96" st_id="12" stage="1" lat="1">
<core>NULL</core>
<MemPortIdVec></MemPortIdVec>
<condition id="19">
<or_exp><and_exp></and_exp></or_exp>
</condition>

<Node id="79" bw="0" op_0_bw="0">
<![CDATA[
arrayctor.loop4.preheader:4  br label %0

]]></Node>
<StgValue><ssdm name=""/></StgValue>
</operation>
</state>

<state id="13" st_id="13">

<operation id="97" st_id="13" stage="1" lat="1">
<core>NULL</core>
<MemPortIdVec></MemPortIdVec>
<condition id="20">
<or_exp><and_exp></and_exp></or_exp>
</condition>

<Node id="81" bw="4" op_0_bw="4" op_1_bw="0">
<![CDATA[
:0  %i_1 = phi i4 [ 1, %arrayctor.loop4.preheader ], [ %i_13, %4 ]

]]></Node>
<StgValue><ssdm name="i_1"/></StgValue>
</operation>

<operation id="98" st_id="13" stage="1" lat="1">
<core>NULL</core>
<MemPortIdVec></MemPortIdVec>
<condition id="20">
<or_exp><and_exp></and_exp></or_exp>
</condition>

<Node id="82" bw="5" op_0_bw="4">
<![CDATA[
:1  %i_1_cast = zext i4 %i_1 to i5

]]></Node>
<StgValue><ssdm name="i_1_cast"/></StgValue>
</operation>

<operation id="99" st_id="13" stage="1" lat="1">
<core>Cmp</core>
<MemPortIdVec></MemPortIdVec>
<condition id="20">
<or_exp><and_exp></and_exp></or_exp>
</condition>

<Node id="83" bw="1" op_0_bw="4" op_1_bw="4">
<![CDATA[
:2  %exitcond4 = icmp eq i4 %i_1, -4

]]></Node>
<StgValue><ssdm name="exitcond4"/></StgValue>
</operation>

<operation id="100" st_id="13" stage="1" lat="1">
<core>NULL</core>
<MemPortIdVec></MemPortIdVec>
<condition id="20">
<or_exp><and_exp></and_exp></or_exp>
</condition>

<Node id="84" bw="32" op_0_bw="32" op_1_bw="64" op_2_bw="64" op_3_bw="64">
<![CDATA[
:3  %empty_60 = call i32 (...)* @_ssdm_op_SpecLoopTripCount(i64 11, i64 11, i64 11)

]]></Node>
<StgValue><ssdm name="empty_60"/></StgValue>
</operation>

<operation id="101" st_id="13" stage="1" lat="1">
<core>NULL</core>
<MemPortIdVec></MemPortIdVec>
<condition id="20">
<or_exp><and_exp></and_exp></or_exp>
</condition>

<Node id="85" bw="0" op_0_bw="1" op_1_bw="0" op_2_bw="0">
<![CDATA[
:4  br i1 %exitcond4, label %.preheader.preheader, label %_ZrsILi48ELb0EE11ap_int_baseIXT_EXT0_EXleT_Li64EEERKS1_i.exit

]]></Node>
<StgValue><ssdm name=""/></StgValue>
</operation>

<operation id="102" st_id="13" stage="1" lat="1">
<core>AddSub</core>
<MemPortIdVec></MemPortIdVec>
<condition id="22">
<or_exp><and_exp><literal name="exitcond4" val="0"/>
</and_exp></or_exp>
</condition>

<Node id="88" bw="4" op_0_bw="4" op_1_bw="4">
<![CDATA[
_ZrsILi48ELb0EE11ap_int_baseIXT_EXT0_EXleT_Li64EEERKS1_i.exit:1  %tmp_185 = add i4 %i_1, -1

]]></Node>
<StgValue><ssdm name="tmp_185"/></StgValue>
</operation>

<operation id="103" st_id="13" stage="1" lat="1">
<core>NULL</core>
<MemPortIdVec></MemPortIdVec>
<condition id="22">
<or_exp><and_exp><literal name="exitcond4" val="0"/>
</and_exp></or_exp>
</condition>

<Node id="89" bw="64" op_0_bw="4">
<![CDATA[
_ZrsILi48ELb0EE11ap_int_baseIXT_EXT0_EXleT_Li64EEERKS1_i.exit:2  %tmp_186 = zext i4 %tmp_185 to i64

]]></Node>
<StgValue><ssdm name="tmp_186"/></StgValue>
</operation>

<operation id="104" st_id="13" stage="1" lat="1">
<core>NULL</core>
<MemPortIdVec></MemPortIdVec>
<condition id="22">
<or_exp><and_exp><literal name="exitcond4" val="0"/>
</and_exp></or_exp>
</condition>

<Node id="90" bw="4" op_0_bw="48" op_1_bw="64" op_2_bw="64">
<![CDATA[
_ZrsILi48ELb0EE11ap_int_baseIXT_EXT0_EXleT_Li64EEERKS1_i.exit:3  %pps_V_addr_5 = getelementptr [12 x i48]* %pps_V, i64 0, i64 %tmp_186

]]></Node>
<StgValue><ssdm name="pps_V_addr_5"/></StgValue>
</operation>

<operation id="105" st_id="13" stage="2" lat="2">
<core>RAM</core>
<MemPortIdVec>0 </MemPortIdVec>
<condition id="22">
<or_exp><and_exp><literal name="exitcond4" val="0"/>
</and_exp></or_exp>
</condition>

<Node id="91" bw="48" op_0_bw="4">
<![CDATA[
_ZrsILi48ELb0EE11ap_int_baseIXT_EXT0_EXleT_Li64EEERKS1_i.exit:4  %pps_V_load = load i48* %pps_V_addr_5, align 8

]]></Node>
<StgValue><ssdm name="pps_V_load"/></StgValue>
</operation>

<operation id="106" st_id="13" stage="1" lat="1">
<core>NULL</core>
<MemPortIdVec></MemPortIdVec>
<condition id="24">
<or_exp><and_exp><literal name="exitcond4" val="1"/>
</and_exp></or_exp>
</condition>

<Node id="134" bw="0" op_0_bw="0">
<![CDATA[
.preheader.preheader:0  br label %.preheader

]]></Node>
<StgValue><ssdm name=""/></StgValue>
</operation>
</state>

<state id="14" st_id="14">

<operation id="107" st_id="14" stage="1" lat="1">
<core>NULL</core>
<MemPortIdVec></MemPortIdVec>
<condition id="25">
<or_exp><and_exp></and_exp></or_exp>
</condition>

<Node id="87" bw="64" op_0_bw="4">
<![CDATA[
_ZrsILi48ELb0EE11ap_int_baseIXT_EXT0_EXleT_Li64EEERKS1_i.exit:0  %tmp_184 = zext i4 %i_1 to i64

]]></Node>
<StgValue><ssdm name="tmp_184"/></StgValue>
</operation>

<operation id="108" st_id="14" stage="1" lat="2">
<core>RAM</core>
<MemPortIdVec>0 </MemPortIdVec>
<condition id="25">
<or_exp><and_exp></and_exp></or_exp>
</condition>

<Node id="91" bw="48" op_0_bw="4">
<![CDATA[
_ZrsILi48ELb0EE11ap_int_baseIXT_EXT0_EXleT_Li64EEERKS1_i.exit:4  %pps_V_load = load i48* %pps_V_addr_5, align 8

]]></Node>
<StgValue><ssdm name="pps_V_load"/></StgValue>
</operation>

<operation id="109" st_id="14" stage="1" lat="1">
<core>NULL</core>
<MemPortIdVec></MemPortIdVec>
<condition id="25">
<or_exp><and_exp></and_exp></or_exp>
</condition>

<Node id="92" bw="31" op_0_bw="31" op_1_bw="48" op_2_bw="32" op_3_bw="32">
<![CDATA[
_ZrsILi48ELb0EE11ap_int_baseIXT_EXT0_EXleT_Li64EEERKS1_i.exit:5  %r_V = call i31 @_ssdm_op_PartSelect.i31.i48.i32.i32(i48 %pps_V_load, i32 17, i32 47)

]]></Node>
<StgValue><ssdm name="r_V"/></StgValue>
</operation>

<operation id="110" st_id="14" stage="1" lat="1">
<core>NULL</core>
<MemPortIdVec></MemPortIdVec>
<condition id="25">
<or_exp><and_exp></and_exp></or_exp>
</condition>

<Node id="93" bw="48" op_0_bw="31">
<![CDATA[
_ZrsILi48ELb0EE11ap_int_baseIXT_EXT0_EXleT_Li64EEERKS1_i.exit:6  %r_V_8 = zext i31 %r_V to i48

]]></Node>
<StgValue><ssdm name="r_V_8"/></StgValue>
</operation>

<operation id="111" st_id="14" stage="1" lat="1">
<core>NULL</core>
<MemPortIdVec></MemPortIdVec>
<condition id="25">
<or_exp><and_exp></and_exp></or_exp>
</condition>

<Node id="94" bw="4" op_0_bw="48" op_1_bw="64" op_2_bw="64">
<![CDATA[
_ZrsILi48ELb0EE11ap_int_baseIXT_EXT0_EXleT_Li64EEERKS1_i.exit:7  %pps_V_addr_6 = getelementptr [12 x i48]* %pps_V, i64 0, i64 %tmp_184

]]></Node>
<StgValue><ssdm name="pps_V_addr_6"/></StgValue>
</operation>

<operation id="112" st_id="14" stage="1" lat="1">
<core>RAM</core>
<MemPortIdVec>0 </MemPortIdVec>
<condition id="25">
<or_exp><and_exp></and_exp></or_exp>
</condition>

<Node id="95" bw="0" op_0_bw="48" op_1_bw="4">
<![CDATA[
_ZrsILi48ELb0EE11ap_int_baseIXT_EXT0_EXleT_Li64EEERKS1_i.exit:8  store i48 %r_V_8, i48* %pps_V_addr_6, align 8

]]></Node>
<StgValue><ssdm name=""/></StgValue>
</operation>

<operation id="113" st_id="14" stage="1" lat="1">
<core>NULL</core>
<MemPortIdVec></MemPortIdVec>
<condition id="25">
<or_exp><and_exp></and_exp></or_exp>
</condition>

<Node id="96" bw="0" op_0_bw="0">
<![CDATA[
_ZrsILi48ELb0EE11ap_int_baseIXT_EXT0_EXleT_Li64EEERKS1_i.exit:9  br label %1

]]></Node>
<StgValue><ssdm name=""/></StgValue>
</operation>
</state>

<state id="15" st_id="15">

<operation id="114" st_id="15" stage="1" lat="1">
<core>NULL</core>
<MemPortIdVec></MemPortIdVec>
<condition id="26">
<or_exp><and_exp></and_exp></or_exp>
</condition>

<Node id="98" bw="3" op_0_bw="3" op_1_bw="0">
<![CDATA[
:0  %j_1 = phi i3 [ 0, %_ZrsILi48ELb0EE11ap_int_baseIXT_EXT0_EXleT_Li64EEERKS1_i.exit ], [ %j_7, %._crit_edge165 ]

]]></Node>
<StgValue><ssdm name="j_1"/></StgValue>
</operation>

<operation id="115" st_id="15" stage="1" lat="1">
<core>NULL</core>
<MemPortIdVec></MemPortIdVec>
<condition id="26">
<or_exp><and_exp></and_exp></or_exp>
</condition>

<Node id="99" bw="5" op_0_bw="3">
<![CDATA[
:1  %j_1_cast3 = zext i3 %j_1 to i5

]]></Node>
<StgValue><ssdm name="j_1_cast3"/></StgValue>
</operation>

<operation id="116" st_id="15" stage="1" lat="1">
<core>NULL</core>
<MemPortIdVec></MemPortIdVec>
<condition id="26">
<or_exp><and_exp></and_exp></or_exp>
</condition>

<Node id="100" bw="4" op_0_bw="3">
<![CDATA[
:2  %j_1_cast3_cast = zext i3 %j_1 to i4

]]></Node>
<StgValue><ssdm name="j_1_cast3_cast"/></StgValue>
</operation>

<operation id="117" st_id="15" stage="1" lat="1">
<core>Cmp</core>
<MemPortIdVec></MemPortIdVec>
<condition id="26">
<or_exp><and_exp></and_exp></or_exp>
</condition>

<Node id="101" bw="1" op_0_bw="3" op_1_bw="3">
<![CDATA[
:3  %exitcond6 = icmp eq i3 %j_1, -2

]]></Node>
<StgValue><ssdm name="exitcond6"/></StgValue>
</operation>

<operation id="118" st_id="15" stage="1" lat="1">
<core>NULL</core>
<MemPortIdVec></MemPortIdVec>
<condition id="26">
<or_exp><and_exp></and_exp></or_exp>
</condition>

<Node id="102" bw="32" op_0_bw="32" op_1_bw="64" op_2_bw="64" op_3_bw="64">
<![CDATA[
:4  %empty_61 = call i32 (...)* @_ssdm_op_SpecLoopTripCount(i64 6, i64 6, i64 6)

]]></Node>
<StgValue><ssdm name="empty_61"/></StgValue>
</operation>

<operation id="119" st_id="15" stage="1" lat="1">
<core>AddSub</core>
<MemPortIdVec></MemPortIdVec>
<condition id="26">
<or_exp><and_exp></and_exp></or_exp>
</condition>

<Node id="103" bw="3" op_0_bw="3" op_1_bw="3">
<![CDATA[
:5  %j_7 = add i3 %j_1, 1

]]></Node>
<StgValue><ssdm name="j_7"/></StgValue>
</operation>

<operation id="120" st_id="15" stage="1" lat="1">
<core>NULL</core>
<MemPortIdVec></MemPortIdVec>
<condition id="26">
<or_exp><and_exp></and_exp></or_exp>
</condition>

<Node id="104" bw="0" op_0_bw="1" op_1_bw="0" op_2_bw="0">
<![CDATA[
:6  br i1 %exitcond6, label %4, label %2

]]></Node>
<StgValue><ssdm name=""/></StgValue>
</operation>

<operation id="121" st_id="15" stage="1" lat="1">
<core>Cmp</core>
<MemPortIdVec></MemPortIdVec>
<condition id="28">
<or_exp><and_exp><literal name="exitcond6" val="0"/>
</and_exp></or_exp>
</condition>

<Node id="106" bw="1" op_0_bw="4" op_1_bw="4">
<![CDATA[
:0  %ult = icmp ult i4 %i_1, %j_1_cast3_cast

]]></Node>
<StgValue><ssdm name="ult"/></StgValue>
</operation>

<operation id="122" st_id="15" stage="1" lat="1">
<core>LogicGate</core>
<MemPortIdVec></MemPortIdVec>
<condition id="28">
<or_exp><and_exp><literal name="exitcond6" val="0"/>
</and_exp></or_exp>
</condition>

<Node id="107" bw="1" op_0_bw="1" op_1_bw="1">
<![CDATA[
:1  %rev5 = xor i1 %ult, true

]]></Node>
<StgValue><ssdm name="rev5"/></StgValue>
</operation>

<operation id="123" st_id="15" stage="1" lat="1">
<core>AddSub</core>
<MemPortIdVec></MemPortIdVec>
<condition id="28">
<or_exp><and_exp><literal name="exitcond6" val="0"/>
</and_exp></or_exp>
</condition>

<Node id="108" bw="5" op_0_bw="5" op_1_bw="5">
<![CDATA[
:2  %tmp_196 = sub i5 %i_1_cast, %j_1_cast3

]]></Node>
<StgValue><ssdm name="tmp_196"/></StgValue>
</operation>

<operation id="124" st_id="15" stage="1" lat="1">
<core>Cmp</core>
<MemPortIdVec></MemPortIdVec>
<condition id="28">
<or_exp><and_exp><literal name="exitcond6" val="0"/>
</and_exp></or_exp>
</condition>

<Node id="109" bw="1" op_0_bw="5" op_1_bw="5">
<![CDATA[
:3  %tmp_197 = icmp slt i5 %tmp_196, 6

]]></Node>
<StgValue><ssdm name="tmp_197"/></StgValue>
</operation>

<operation id="125" st_id="15" stage="1" lat="1">
<core>LogicGate</core>
<MemPortIdVec></MemPortIdVec>
<condition id="28">
<or_exp><and_exp><literal name="exitcond6" val="0"/>
</and_exp></or_exp>
</condition>

<Node id="110" bw="1" op_0_bw="1" op_1_bw="1">
<![CDATA[
:4  %or_cond = and i1 %rev5, %tmp_197

]]></Node>
<StgValue><ssdm name="or_cond"/></StgValue>
</operation>

<operation id="126" st_id="15" stage="1" lat="1">
<core>NULL</core>
<MemPortIdVec></MemPortIdVec>
<condition id="28">
<or_exp><and_exp><literal name="exitcond6" val="0"/>
</and_exp></or_exp>
</condition>

<Node id="111" bw="0" op_0_bw="1" op_1_bw="0" op_2_bw="0">
<![CDATA[
:5  br i1 %or_cond, label %3, label %._crit_edge165

]]></Node>
<StgValue><ssdm name=""/></StgValue>
</operation>

<operation id="127" st_id="15" stage="1" lat="1">
<core>NULL</core>
<MemPortIdVec></MemPortIdVec>
<condition id="30">
<or_exp><and_exp><literal name="exitcond6" val="0"/>
<literal name="or_cond" val="1"/>
</and_exp></or_exp>
</condition>

<Node id="113" bw="7" op_0_bw="5">
<![CDATA[
:0  %tmp_198_cast = sext i5 %tmp_196 to i7

]]></Node>
<StgValue><ssdm name="tmp_198_cast"/></StgValue>
</operation>

<operation id="128" st_id="15" stage="1" lat="1">
<core>NULL</core>
<MemPortIdVec></MemPortIdVec>
<condition id="30">
<or_exp><and_exp><literal name="exitcond6" val="0"/>
<literal name="or_cond" val="1"/>
</and_exp></or_exp>
</condition>

<Node id="114" bw="6" op_0_bw="6" op_1_bw="3" op_2_bw="3">
<![CDATA[
:1  %tmp_294 = call i6 @_ssdm_op_BitConcatenate.i6.i3.i3(i3 %j_1, i3 0)

]]></Node>
<StgValue><ssdm name="tmp_294"/></StgValue>
</operation>

<operation id="129" st_id="15" stage="1" lat="1">
<core>NULL</core>
<MemPortIdVec></MemPortIdVec>
<condition id="30">
<or_exp><and_exp><literal name="exitcond6" val="0"/>
<literal name="or_cond" val="1"/>
</and_exp></or_exp>
</condition>

<Node id="115" bw="7" op_0_bw="6">
<![CDATA[
:2  %p_shl2_cast = zext i6 %tmp_294 to i7

]]></Node>
<StgValue><ssdm name="p_shl2_cast"/></StgValue>
</operation>

<operation id="130" st_id="15" stage="1" lat="1">
<core>NULL</core>
<MemPortIdVec></MemPortIdVec>
<condition id="30">
<or_exp><and_exp><literal name="exitcond6" val="0"/>
<literal name="or_cond" val="1"/>
</and_exp></or_exp>
</condition>

<Node id="116" bw="4" op_0_bw="4" op_1_bw="3" op_2_bw="1">
<![CDATA[
:3  %tmp_295 = call i4 @_ssdm_op_BitConcatenate.i4.i3.i1(i3 %j_1, i1 false)

]]></Node>
<StgValue><ssdm name="tmp_295"/></StgValue>
</operation>

<operation id="131" st_id="15" stage="1" lat="1">
<core>NULL</core>
<MemPortIdVec></MemPortIdVec>
<condition id="30">
<or_exp><and_exp><literal name="exitcond6" val="0"/>
<literal name="or_cond" val="1"/>
</and_exp></or_exp>
</condition>

<Node id="117" bw="7" op_0_bw="4">
<![CDATA[
:4  %p_shl3_cast = zext i4 %tmp_295 to i7

]]></Node>
<StgValue><ssdm name="p_shl3_cast"/></StgValue>
</operation>

<operation id="132" st_id="15" stage="1" lat="1">
<core>TAddSub</core>
<MemPortIdVec></MemPortIdVec>
<condition id="30">
<or_exp><and_exp><literal name="exitcond6" val="0"/>
<literal name="or_cond" val="1"/>
</and_exp></or_exp>
</condition>

<Node id="118" bw="7" op_0_bw="7" op_1_bw="7">
<![CDATA[
:5  %tmp_296 = sub i7 %p_shl2_cast, %p_shl3_cast

]]></Node>
<StgValue><ssdm name="tmp_296"/></StgValue>
</operation>

<operation id="133" st_id="15" stage="1" lat="1">
<core>TAddSub</core>
<MemPortIdVec></MemPortIdVec>
<condition id="30">
<or_exp><and_exp><literal name="exitcond6" val="0"/>
<literal name="or_cond" val="1"/>
</and_exp></or_exp>
</condition>

<Node id="119" bw="7" op_0_bw="7" op_1_bw="7">
<![CDATA[
:6  %tmp_297 = add i7 %tmp_296, %tmp_198_cast

]]></Node>
<StgValue><ssdm name="tmp_297"/></StgValue>
</operation>

<operation id="134" st_id="15" stage="1" lat="1">
<core>NULL</core>
<MemPortIdVec></MemPortIdVec>
<condition id="30">
<or_exp><and_exp><literal name="exitcond6" val="0"/>
<literal name="or_cond" val="1"/>
</and_exp></or_exp>
</condition>

<Node id="120" bw="64" op_0_bw="7">
<![CDATA[
:7  %tmp_303_cast = sext i7 %tmp_297 to i64

]]></Node>
<StgValue><ssdm name="tmp_303_cast"/></StgValue>
</operation>

<operation id="135" st_id="15" stage="1" lat="1">
<core>NULL</core>
<MemPortIdVec></MemPortIdVec>
<condition id="30">
<or_exp><and_exp><literal name="exitcond6" val="0"/>
<literal name="or_cond" val="1"/>
</and_exp></or_exp>
</condition>

<Node id="121" bw="6" op_0_bw="34" op_1_bw="64" op_2_bw="64">
<![CDATA[
:8  %pp_V_addr_4 = getelementptr [36 x i34]* %pp_V, i64 0, i64 %tmp_303_cast

]]></Node>
<StgValue><ssdm name="pp_V_addr_4"/></StgValue>
</operation>

<operation id="136" st_id="15" stage="2" lat="2">
<core>RAM</core>
<MemPortIdVec>0 </MemPortIdVec>
<condition id="30">
<or_exp><and_exp><literal name="exitcond6" val="0"/>
<literal name="or_cond" val="1"/>
</and_exp></or_exp>
</condition>

<Node id="122" bw="34" op_0_bw="6">
<![CDATA[
:9  %pp_V_load_2 = load i34* %pp_V_addr_4, align 8

]]></Node>
<StgValue><ssdm name="pp_V_load_2"/></StgValue>
</operation>

<operation id="137" st_id="15" stage="2" lat="2">
<core>RAM</core>
<MemPortIdVec>0 </MemPortIdVec>
<condition id="30">
<or_exp><and_exp><literal name="exitcond6" val="0"/>
<literal name="or_cond" val="1"/>
</and_exp></or_exp>
</condition>

<Node id="124" bw="48" op_0_bw="4">
<![CDATA[
:11  %pps_V_load_4 = load i48* %pps_V_addr_6, align 8

]]></Node>
<StgValue><ssdm name="pps_V_load_4"/></StgValue>
</operation>

<operation id="138" st_id="15" stage="1" lat="1">
<core>AddSub</core>
<MemPortIdVec></MemPortIdVec>
<condition id="32">
<or_exp><and_exp><literal name="exitcond6" val="1"/>
</and_exp></or_exp>
</condition>

<Node id="131" bw="4" op_0_bw="4" op_1_bw="4">
<![CDATA[
:0  %i_13 = add i4 %i_1, 1

]]></Node>
<StgValue><ssdm name="i_13"/></StgValue>
</operation>

<operation id="139" st_id="15" stage="1" lat="1">
<core>NULL</core>
<MemPortIdVec></MemPortIdVec>
<condition id="32">
<or_exp><and_exp><literal name="exitcond6" val="1"/>
</and_exp></or_exp>
</condition>

<Node id="132" bw="0" op_0_bw="0">
<![CDATA[
:1  br label %0

]]></Node>
<StgValue><ssdm name=""/></StgValue>
</operation>
</state>

<state id="16" st_id="16">

<operation id="140" st_id="16" stage="1" lat="2">
<core>RAM</core>
<MemPortIdVec>0 </MemPortIdVec>
<condition id="33">
<or_exp><and_exp><literal name="or_cond" val="1"/>
</and_exp></or_exp>
</condition>

<Node id="122" bw="34" op_0_bw="6">
<![CDATA[
:9  %pp_V_load_2 = load i34* %pp_V_addr_4, align 8

]]></Node>
<StgValue><ssdm name="pp_V_load_2"/></StgValue>
</operation>

<operation id="141" st_id="16" stage="1" lat="1">
<core>NULL</core>
<MemPortIdVec></MemPortIdVec>
<condition id="33">
<or_exp><and_exp><literal name="or_cond" val="1"/>
</and_exp></or_exp>
</condition>

<Node id="123" bw="48" op_0_bw="34">
<![CDATA[
:10  %tmp_199 = zext i34 %pp_V_load_2 to i48

]]></Node>
<StgValue><ssdm name="tmp_199"/></StgValue>
</operation>

<operation id="142" st_id="16" stage="1" lat="2">
<core>RAM</core>
<MemPortIdVec>0 </MemPortIdVec>
<condition id="33">
<or_exp><and_exp><literal name="or_cond" val="1"/>
</and_exp></or_exp>
</condition>

<Node id="124" bw="48" op_0_bw="4">
<![CDATA[
:11  %pps_V_load_4 = load i48* %pps_V_addr_6, align 8

]]></Node>
<StgValue><ssdm name="pps_V_load_4"/></StgValue>
</operation>

<operation id="143" st_id="16" stage="1" lat="1">
<core>AddSub</core>
<MemPortIdVec></MemPortIdVec>
<condition id="33">
<or_exp><and_exp><literal name="or_cond" val="1"/>
</and_exp></or_exp>
</condition>

<Node id="125" bw="48" op_0_bw="48" op_1_bw="48">
<![CDATA[
:12  %tmp_200 = add i48 %tmp_199, %pps_V_load_4

]]></Node>
<StgValue><ssdm name="tmp_200"/></StgValue>
</operation>

<operation id="144" st_id="16" stage="1" lat="1">
<core>RAM</core>
<MemPortIdVec>0 </MemPortIdVec>
<condition id="33">
<or_exp><and_exp><literal name="or_cond" val="1"/>
</and_exp></or_exp>
</condition>

<Node id="126" bw="0" op_0_bw="48" op_1_bw="4">
<![CDATA[
:13  store i48 %tmp_200, i48* %pps_V_addr_6, align 8

]]></Node>
<StgValue><ssdm name=""/></StgValue>
</operation>

<operation id="145" st_id="16" stage="1" lat="1">
<core>NULL</core>
<MemPortIdVec></MemPortIdVec>
<condition id="33">
<or_exp><and_exp><literal name="or_cond" val="1"/>
</and_exp></or_exp>
</condition>

<Node id="127" bw="0" op_0_bw="0">
<![CDATA[
:14  br label %._crit_edge165

]]></Node>
<StgValue><ssdm name=""/></StgValue>
</operation>

<operation id="146" st_id="16" stage="1" lat="1">
<core>NULL</core>
<MemPortIdVec></MemPortIdVec>
<condition id="36">
<or_exp><and_exp></and_exp></or_exp>
</condition>

<Node id="129" bw="0" op_0_bw="0">
<![CDATA[
._crit_edge165:0  br label %1

]]></Node>
<StgValue><ssdm name=""/></StgValue>
</operation>
</state>

<state id="17" st_id="17">

<operation id="147" st_id="17" stage="1" lat="1">
<core>NULL</core>
<MemPortIdVec></MemPortIdVec>
<condition id="37">
<or_exp><and_exp></and_exp></or_exp>
</condition>

<Node id="136" bw="188" op_0_bw="188" op_1_bw="0">
<![CDATA[
.preheader:0  %p_Val2_34 = phi i188 [ %p_Result_s, %._crit_edge166 ], [ undef, %.preheader.preheader ]

]]></Node>
<StgValue><ssdm name="p_Val2_34"/></StgValue>
</operation>

<operation id="148" st_id="17" stage="1" lat="1">
<core>NULL</core>
<MemPortIdVec></MemPortIdVec>
<condition id="37">
<or_exp><and_exp></and_exp></or_exp>
</condition>

<Node id="137" bw="4" op_0_bw="4" op_1_bw="0">
<![CDATA[
.preheader:1  %i_2 = phi i4 [ %i_12, %._crit_edge166 ], [ 0, %.preheader.preheader ]

]]></Node>
<StgValue><ssdm name="i_2"/></StgValue>
</operation>

<operation id="149" st_id="17" stage="1" lat="1">
<core>Cmp</core>
<MemPortIdVec></MemPortIdVec>
<condition id="37">
<or_exp><and_exp></and_exp></or_exp>
</condition>

<Node id="138" bw="1" op_0_bw="4" op_1_bw="4">
<![CDATA[
.preheader:2  %exitcond = icmp eq i4 %i_2, -4

]]></Node>
<StgValue><ssdm name="exitcond"/></StgValue>
</operation>

<operation id="150" st_id="17" stage="1" lat="1">
<core>NULL</core>
<MemPortIdVec></MemPortIdVec>
<condition id="37">
<or_exp><and_exp></and_exp></or_exp>
</condition>

<Node id="139" bw="32" op_0_bw="32" op_1_bw="64" op_2_bw="64" op_3_bw="64">
<![CDATA[
.preheader:3  %empty_62 = call i32 (...)* @_ssdm_op_SpecLoopTripCount(i64 12, i64 12, i64 12)

]]></Node>
<StgValue><ssdm name="empty_62"/></StgValue>
</operation>

<operation id="151" st_id="17" stage="1" lat="1">
<core>AddSub</core>
<MemPortIdVec></MemPortIdVec>
<condition id="37">
<or_exp><and_exp></and_exp></or_exp>
</condition>

<Node id="140" bw="4" op_0_bw="4" op_1_bw="4">
<![CDATA[
.preheader:4  %i_12 = add i4 %i_2, 1

]]></Node>
<StgValue><ssdm name="i_12"/></StgValue>
</operation>

<operation id="152" st_id="17" stage="1" lat="1">
<core>NULL</core>
<MemPortIdVec></MemPortIdVec>
<condition id="37">
<or_exp><and_exp></and_exp></or_exp>
</condition>

<Node id="141" bw="0" op_0_bw="1" op_1_bw="0" op_2_bw="0">
<![CDATA[
.preheader:5  br i1 %exitcond, label %5, label %._crit_edge166

]]></Node>
<StgValue><ssdm name=""/></StgValue>
</operation>

<operation id="153" st_id="17" stage="1" lat="1">
<core>NULL</core>
<MemPortIdVec></MemPortIdVec>
<condition id="39">
<or_exp><and_exp><literal name="exitcond" val="0"/>
</and_exp></or_exp>
</condition>

<Node id="143" bw="8" op_0_bw="8" op_1_bw="4" op_2_bw="4">
<![CDATA[
._crit_edge166:0  %Li = call i8 @_ssdm_op_BitConcatenate.i8.i4.i4(i4 %i_2, i4 %i_2)

]]></Node>
<StgValue><ssdm name="Li"/></StgValue>
</operation>

<operation id="154" st_id="17" stage="1" lat="1">
<core>AddSub</core>
<MemPortIdVec></MemPortIdVec>
<condition id="39">
<or_exp><and_exp><literal name="exitcond" val="0"/>
</and_exp></or_exp>
</condition>

<Node id="144" bw="8" op_0_bw="8" op_1_bw="8">
<![CDATA[
._crit_edge166:1  %Ui = add i8 16, %Li

]]></Node>
<StgValue><ssdm name="Ui"/></StgValue>
</operation>

<operation id="155" st_id="17" stage="1" lat="1">
<core>Cmp</core>
<MemPortIdVec></MemPortIdVec>
<condition id="39">
<or_exp><and_exp><literal name="exitcond" val="0"/>
</and_exp></or_exp>
</condition>

<Node id="145" bw="1" op_0_bw="8" op_1_bw="8">
<![CDATA[
._crit_edge166:2  %tmp_193 = icmp ugt i8 %Ui, -69

]]></Node>
<StgValue><ssdm name="tmp_193"/></StgValue>
</operation>

<operation id="156" st_id="17" stage="1" lat="1">
<core>Sel</core>
<MemPortIdVec></MemPortIdVec>
<condition id="39">
<or_exp><and_exp><literal name="exitcond" val="0"/>
</and_exp></or_exp>
</condition>

<Node id="146" bw="8" op_0_bw="1" op_1_bw="8" op_2_bw="8">
<![CDATA[
._crit_edge166:3  %Hi_assign = select i1 %tmp_193, i8 -69, i8 %Ui

]]></Node>
<StgValue><ssdm name="Hi_assign"/></StgValue>
</operation>

<operation id="157" st_id="17" stage="1" lat="1">
<core>NULL</core>
<MemPortIdVec></MemPortIdVec>
<condition id="39">
<or_exp><and_exp><literal name="exitcond" val="0"/>
</and_exp></or_exp>
</condition>

<Node id="147" bw="64" op_0_bw="4">
<![CDATA[
._crit_edge166:4  %tmp_194 = zext i4 %i_2 to i64

]]></Node>
<StgValue><ssdm name="tmp_194"/></StgValue>
</operation>

<operation id="158" st_id="17" stage="1" lat="1">
<core>NULL</core>
<MemPortIdVec></MemPortIdVec>
<condition id="39">
<or_exp><and_exp><literal name="exitcond" val="0"/>
</and_exp></or_exp>
</condition>

<Node id="148" bw="4" op_0_bw="48" op_1_bw="64" op_2_bw="64">
<![CDATA[
._crit_edge166:5  %pps_V_addr_7 = getelementptr [12 x i48]* %pps_V, i64 0, i64 %tmp_194

]]></Node>
<StgValue><ssdm name="pps_V_addr_7"/></StgValue>
</operation>

<operation id="159" st_id="17" stage="2" lat="2">
<core>RAM</core>
<MemPortIdVec>0 </MemPortIdVec>
<condition id="39">
<or_exp><and_exp><literal name="exitcond" val="0"/>
</and_exp></or_exp>
</condition>

<Node id="149" bw="48" op_0_bw="4">
<![CDATA[
._crit_edge166:6  %p_Val2_s = load i48* %pps_V_addr_7, align 8

]]></Node>
<StgValue><ssdm name="p_Val2_s"/></StgValue>
</operation>

<operation id="160" st_id="17" stage="1" lat="1">
<core>NULL</core>
<MemPortIdVec></MemPortIdVec>
<condition id="41">
<or_exp><and_exp><literal name="exitcond" val="1"/>
</and_exp></or_exp>
</condition>

<Node id="173" bw="0" op_0_bw="188">
<![CDATA[
:0  ret i188 %p_Val2_34

]]></Node>
<StgValue><ssdm name=""/></StgValue>
</operation>
</state>

<state id="18" st_id="18">

<operation id="161" st_id="18" stage="1" lat="2">
<core>RAM</core>
<MemPortIdVec>0 </MemPortIdVec>
<condition id="42">
<or_exp><and_exp></and_exp></or_exp>
</condition>

<Node id="149" bw="48" op_0_bw="4">
<![CDATA[
._crit_edge166:6  %p_Val2_s = load i48* %pps_V_addr_7, align 8

]]></Node>
<StgValue><ssdm name="p_Val2_s"/></StgValue>
</operation>

<operation id="162" st_id="18" stage="1" lat="1">
<core>NULL</core>
<MemPortIdVec></MemPortIdVec>
<condition id="42">
<or_exp><and_exp></and_exp></or_exp>
</condition>

<Node id="150" bw="17" op_0_bw="48">
<![CDATA[
._crit_edge166:7  %tmp_387 = trunc i48 %p_Val2_s to i17

]]></Node>
<StgValue><ssdm name="tmp_387"/></StgValue>
</operation>

<operation id="163" st_id="18" stage="1" lat="1">
<core>NULL</core>
<MemPortIdVec></MemPortIdVec>
<condition id="42">
<or_exp><and_exp></and_exp></or_exp>
</condition>

<Node id="151" bw="188" op_0_bw="17">
<![CDATA[
._crit_edge166:8  %loc_V = zext i17 %tmp_387 to i188

]]></Node>
<StgValue><ssdm name="loc_V"/></StgValue>
</operation>

<operation id="164" st_id="18" stage="1" lat="1">
<core>Cmp</core>
<MemPortIdVec></MemPortIdVec>
<condition id="42">
<or_exp><and_exp></and_exp></or_exp>
</condition>

<Node id="152" bw="1" op_0_bw="8" op_1_bw="8">
<![CDATA[
._crit_edge166:9  %tmp_388 = icmp ugt i8 %Li, %Hi_assign

]]></Node>
<StgValue><ssdm name="tmp_388"/></StgValue>
</operation>

<operation id="165" st_id="18" stage="1" lat="1">
<core>AddSub</core>
<MemPortIdVec></MemPortIdVec>
<condition id="42">
<or_exp><and_exp></and_exp></or_exp>
</condition>

<Node id="153" bw="8" op_0_bw="8" op_1_bw="8">
<![CDATA[
._crit_edge166:10  %tmp_389 = sub i8 -69, %Li

]]></Node>
<StgValue><ssdm name="tmp_389"/></StgValue>
</operation>

<operation id="166" st_id="18" stage="1" lat="1">
<core>Sel</core>
<MemPortIdVec></MemPortIdVec>
<condition id="42">
<or_exp><and_exp></and_exp></or_exp>
</condition>

<Node id="154" bw="8" op_0_bw="1" op_1_bw="8" op_2_bw="8">
<![CDATA[
._crit_edge166:11  %tmp_390 = select i1 %tmp_388, i8 %Li, i8 %Hi_assign

]]></Node>
<StgValue><ssdm name="tmp_390"/></StgValue>
</operation>

<operation id="167" st_id="18" stage="1" lat="1">
<core>Sel</core>
<MemPortIdVec></MemPortIdVec>
<condition id="42">
<or_exp><and_exp></and_exp></or_exp>
</condition>

<Node id="155" bw="8" op_0_bw="1" op_1_bw="8" op_2_bw="8">
<![CDATA[
._crit_edge166:12  %tmp_391 = select i1 %tmp_388, i8 %Hi_assign, i8 %Li

]]></Node>
<StgValue><ssdm name="tmp_391"/></StgValue>
</operation>

<operation id="168" st_id="18" stage="1" lat="1">
<core>Sel</core>
<MemPortIdVec></MemPortIdVec>
<condition id="42">
<or_exp><and_exp></and_exp></or_exp>
</condition>

<Node id="156" bw="8" op_0_bw="1" op_1_bw="8" op_2_bw="8">
<![CDATA[
._crit_edge166:13  %tmp_392 = select i1 %tmp_388, i8 %tmp_389, i8 %Li

]]></Node>
<StgValue><ssdm name="tmp_392"/></StgValue>
</operation>

<operation id="169" st_id="18" stage="1" lat="1">
<core>AddSub</core>
<MemPortIdVec></MemPortIdVec>
<condition id="42">
<or_exp><and_exp></and_exp></or_exp>
</condition>

<Node id="157" bw="8" op_0_bw="8" op_1_bw="8">
<![CDATA[
._crit_edge166:14  %tmp_393 = sub i8 -69, %tmp_390

]]></Node>
<StgValue><ssdm name="tmp_393"/></StgValue>
</operation>

<operation id="170" st_id="18" stage="1" lat="1">
<core>NULL</core>
<MemPortIdVec></MemPortIdVec>
<condition id="42">
<or_exp><and_exp></and_exp></or_exp>
</condition>

<Node id="158" bw="188" op_0_bw="8">
<![CDATA[
._crit_edge166:15  %tmp_394 = zext i8 %tmp_392 to i188

]]></Node>
<StgValue><ssdm name="tmp_394"/></StgValue>
</operation>

<operation id="171" st_id="18" stage="1" lat="1">
<core>NULL</core>
<MemPortIdVec></MemPortIdVec>
<condition id="42">
<or_exp><and_exp></and_exp></or_exp>
</condition>

<Node id="159" bw="188" op_0_bw="8">
<![CDATA[
._crit_edge166:16  %tmp_395 = zext i8 %tmp_391 to i188

]]></Node>
<StgValue><ssdm name="tmp_395"/></StgValue>
</operation>

<operation id="172" st_id="18" stage="1" lat="1">
<core>NULL</core>
<MemPortIdVec></MemPortIdVec>
<condition id="42">
<or_exp><and_exp></and_exp></or_exp>
</condition>

<Node id="160" bw="188" op_0_bw="8">
<![CDATA[
._crit_edge166:17  %tmp_396 = zext i8 %tmp_393 to i188

]]></Node>
<StgValue><ssdm name="tmp_396"/></StgValue>
</operation>

<operation id="173" st_id="18" stage="1" lat="1">
<core>Shift</core>
<MemPortIdVec></MemPortIdVec>
<condition id="42">
<or_exp><and_exp></and_exp></or_exp>
</condition>

<Node id="161" bw="188" op_0_bw="188" op_1_bw="188">
<![CDATA[
._crit_edge166:18  %tmp_397 = shl i188 %loc_V, %tmp_394

]]></Node>
<StgValue><ssdm name="tmp_397"/></StgValue>
</operation>

<operation id="174" st_id="18" stage="1" lat="1">
<core>NULL</core>
<MemPortIdVec></MemPortIdVec>
<condition id="42">
<or_exp><and_exp></and_exp></or_exp>
</condition>

<Node id="162" bw="188" op_0_bw="188" op_1_bw="188" op_2_bw="32" op_3_bw="32">
<![CDATA[
._crit_edge166:19  %tmp_398 = call i188 @llvm.part.select.i188(i188 %tmp_397, i32 187, i32 0)

]]></Node>
<StgValue><ssdm name="tmp_398"/></StgValue>
</operation>

<operation id="175" st_id="18" stage="1" lat="1">
<core>Sel</core>
<MemPortIdVec></MemPortIdVec>
<condition id="42">
<or_exp><and_exp></and_exp></or_exp>
</condition>

<Node id="163" bw="188" op_0_bw="1" op_1_bw="188" op_2_bw="188">
<![CDATA[
._crit_edge166:20  %tmp_399 = select i1 %tmp_388, i188 %tmp_398, i188 %tmp_397

]]></Node>
<StgValue><ssdm name="tmp_399"/></StgValue>
</operation>

<operation id="176" st_id="18" stage="1" lat="1">
<core>Shift</core>
<MemPortIdVec></MemPortIdVec>
<condition id="42">
<or_exp><and_exp></and_exp></or_exp>
</condition>

<Node id="164" bw="188" op_0_bw="188" op_1_bw="188">
<![CDATA[
._crit_edge166:21  %tmp_400 = shl i188 -1, %tmp_395

]]></Node>
<StgValue><ssdm name="tmp_400"/></StgValue>
</operation>

<operation id="177" st_id="18" stage="1" lat="1">
<core>Shift</core>
<MemPortIdVec></MemPortIdVec>
<condition id="42">
<or_exp><and_exp></and_exp></or_exp>
</condition>

<Node id="165" bw="188" op_0_bw="188" op_1_bw="188">
<![CDATA[
._crit_edge166:22  %tmp_401 = lshr i188 -1, %tmp_396

]]></Node>
<StgValue><ssdm name="tmp_401"/></StgValue>
</operation>

<operation id="178" st_id="18" stage="1" lat="1">
<core>LogicGate</core>
<MemPortIdVec></MemPortIdVec>
<condition id="42">
<or_exp><and_exp></and_exp></or_exp>
</condition>

<Node id="166" bw="188" op_0_bw="188" op_1_bw="188">
<![CDATA[
._crit_edge166:23  %p_demorgan = and i188 %tmp_400, %tmp_401

]]></Node>
<StgValue><ssdm name="p_demorgan"/></StgValue>
</operation>

<operation id="179" st_id="18" stage="1" lat="1">
<core>LogicGate</core>
<MemPortIdVec></MemPortIdVec>
<condition id="42">
<or_exp><and_exp></and_exp></or_exp>
</condition>

<Node id="167" bw="188" op_0_bw="188" op_1_bw="188">
<![CDATA[
._crit_edge166:24  %tmp_402 = xor i188 %p_demorgan, -1

]]></Node>
<StgValue><ssdm name="tmp_402"/></StgValue>
</operation>

<operation id="180" st_id="18" stage="1" lat="1">
<core>LogicGate</core>
<MemPortIdVec></MemPortIdVec>
<condition id="42">
<or_exp><and_exp></and_exp></or_exp>
</condition>

<Node id="168" bw="188" op_0_bw="188" op_1_bw="188">
<![CDATA[
._crit_edge166:25  %tmp_403 = and i188 %p_Val2_34, %tmp_402

]]></Node>
<StgValue><ssdm name="tmp_403"/></StgValue>
</operation>

<operation id="181" st_id="18" stage="1" lat="1">
<core>LogicGate</core>
<MemPortIdVec></MemPortIdVec>
<condition id="42">
<or_exp><and_exp></and_exp></or_exp>
</condition>

<Node id="169" bw="188" op_0_bw="188" op_1_bw="188">
<![CDATA[
._crit_edge166:26  %tmp_404 = and i188 %tmp_399, %p_demorgan

]]></Node>
<StgValue><ssdm name="tmp_404"/></StgValue>
</operation>

<operation id="182" st_id="18" stage="1" lat="1">
<core>LogicGate</core>
<MemPortIdVec></MemPortIdVec>
<condition id="42">
<or_exp><and_exp></and_exp></or_exp>
</condition>

<Node id="170" bw="188" op_0_bw="188" op_1_bw="188">
<![CDATA[
._crit_edge166:27  %p_Result_s = or i188 %tmp_403, %tmp_404

]]></Node>
<StgValue><ssdm name="p_Result_s"/></StgValue>
</operation>

<operation id="183" st_id="18" stage="1" lat="1">
<core>NULL</core>
<MemPortIdVec></MemPortIdVec>
<condition id="42">
<or_exp><and_exp></and_exp></or_exp>
</condition>

<Node id="171" bw="0" op_0_bw="0">
<![CDATA[
._crit_edge166:28  br label %.preheader

]]></Node>
<StgValue><ssdm name=""/></StgValue>
</operation>
</state>
</state_list>


<ports>
<port id="211" name="a_V" dir="0" iftype="0">
<core>NULL</core><StgValue><ssdm name="a_V"/></StgValue>
</port>
</ports>


<dataflows>
<dataflow id="213" from="_ssdm_op_Read.ap_auto.i78" to="a_V_read" fromId="212" toId="19">
</dataflow>
<dataflow id="214" from="a_V" to="a_V_read" fromId="211" toId="19">
</dataflow>
<dataflow id="215" from="a_V_read" to="a_V_cast" fromId="19" toId="20">
</dataflow>
<dataflow id="217" from="StgValue_216" to="pp_V" fromId="216" toId="21">
</dataflow>
<dataflow id="218" from="pp_V" to="pp_V_addr" fromId="21" toId="22">
</dataflow>
<dataflow id="220" from="StgValue_219" to="pp_V_addr" fromId="219" toId="22">
</dataflow>
<dataflow id="221" from="StgValue_219" to="pp_V_addr" fromId="219" toId="22">
</dataflow>
<dataflow id="222" from="StgValue_216" to="pps_V" fromId="216" toId="23">
</dataflow>
<dataflow id="224" from="StgValue_223" to="i" fromId="223" toId="25">
<condition id="98">
<or_exp><and_exp></and_exp></or_exp>
</condition>
</dataflow>
<dataflow id="225" from="StgValue_24" to="i" fromId="24" toId="25">
</dataflow>
<dataflow id="226" from="i_11" to="i" fromId="28" toId="25">
<BackEdge/>
<condition id="99">
<or_exp><and_exp><literal name="exitcond5" val="1"/>
</and_exp></or_exp>
</condition>
</dataflow>
<dataflow id="227" from="StgValue_67" to="i" fromId="67" toId="25">
<BackEdge/>
</dataflow>
<dataflow id="228" from="i" to="exitcond3" fromId="25" toId="26">
</dataflow>
<dataflow id="230" from="StgValue_229" to="exitcond3" fromId="229" toId="26">
</dataflow>
<dataflow id="232" from="_ssdm_op_SpecLoopTripCount" to="empty" fromId="231" toId="27">
</dataflow>
<dataflow id="234" from="StgValue_233" to="empty" fromId="233" toId="27">
</dataflow>
<dataflow id="235" from="StgValue_233" to="empty" fromId="233" toId="27">
</dataflow>
<dataflow id="236" from="StgValue_233" to="empty" fromId="233" toId="27">
</dataflow>
<dataflow id="237" from="i" to="i_11" fromId="25" toId="28">
</dataflow>
<dataflow id="239" from="StgValue_238" to="i_11" fromId="238" toId="28">
</dataflow>
<dataflow id="240" from="exitcond3" to="StgValue_29" fromId="26" toId="29">
</dataflow>
<dataflow id="241" from="i" to="tmp_s" fromId="25" toId="30">
</dataflow>
<dataflow id="243" from="StgValue_242" to="tmp_s" fromId="242" toId="30">
</dataflow>
<dataflow id="245" from="_ssdm_op_BitConcatenate.i6.i3.i3" to="tmp_290" fromId="244" toId="31">
</dataflow>
<dataflow id="246" from="i" to="tmp_290" fromId="25" toId="31">
</dataflow>
<dataflow id="247" from="StgValue_223" to="tmp_290" fromId="223" toId="31">
</dataflow>
<dataflow id="248" from="tmp_290" to="p_shl_cast" fromId="31" toId="32">
</dataflow>
<dataflow id="250" from="_ssdm_op_BitConcatenate.i4.i3.i1" to="tmp_291" fromId="249" toId="33">
</dataflow>
<dataflow id="251" from="i" to="tmp_291" fromId="25" toId="33">
</dataflow>
<dataflow id="253" from="StgValue_252" to="tmp_291" fromId="252" toId="33">
</dataflow>
<dataflow id="254" from="tmp_291" to="p_shl1_cast" fromId="33" toId="34">
</dataflow>
<dataflow id="255" from="p_shl_cast" to="tmp_292" fromId="32" toId="35">
</dataflow>
<dataflow id="256" from="p_shl1_cast" to="tmp_292" fromId="34" toId="35">
</dataflow>
<dataflow id="258" from="_ssdm_op_BitConcatenate.i7.i3.i1.i3" to="Lo_assign" fromId="257" toId="36">
</dataflow>
<dataflow id="259" from="i" to="Lo_assign" fromId="25" toId="36">
</dataflow>
<dataflow id="260" from="StgValue_252" to="Lo_assign" fromId="252" toId="36">
</dataflow>
<dataflow id="261" from="i" to="Lo_assign" fromId="25" toId="36">
</dataflow>
<dataflow id="262" from="Lo_assign" to="tmp_183" fromId="36" toId="37">
</dataflow>
<dataflow id="264" from="StgValue_263" to="tmp_183" fromId="263" toId="37">
</dataflow>
<dataflow id="265" from="tmp_s" to="Ui_2" fromId="30" toId="38">
</dataflow>
<dataflow id="267" from="StgValue_266" to="Ui_2" fromId="266" toId="38">
</dataflow>
<dataflow id="268" from="tmp_183" to="Ui_2" fromId="37" toId="38">
</dataflow>
<dataflow id="269" from="pp_V_addr" to="pp_V_load" fromId="22" toId="40">
</dataflow>
<dataflow id="270" from="j_6" to="j" fromId="44" toId="41">
<BackEdge/>
<condition id="100">
<or_exp><and_exp></and_exp></or_exp>
</condition>
</dataflow>
<dataflow id="271" from="StgValue_91" to="j" fromId="91" toId="41">
<BackEdge/>
</dataflow>
<dataflow id="272" from="StgValue_223" to="j" fromId="223" toId="41">
<condition id="101">
<or_exp><and_exp><literal name="exitcond3" val="0"/>
</and_exp></or_exp>
</condition>
</dataflow>
<dataflow id="273" from="StgValue_39" to="j" fromId="39" toId="41">
</dataflow>
<dataflow id="274" from="j" to="exitcond5" fromId="41" toId="42">
</dataflow>
<dataflow id="275" from="StgValue_229" to="exitcond5" fromId="229" toId="42">
</dataflow>
<dataflow id="276" from="_ssdm_op_SpecLoopTripCount" to="empty_59" fromId="231" toId="43">
</dataflow>
<dataflow id="277" from="StgValue_233" to="empty_59" fromId="233" toId="43">
</dataflow>
<dataflow id="278" from="StgValue_233" to="empty_59" fromId="233" toId="43">
</dataflow>
<dataflow id="279" from="StgValue_233" to="empty_59" fromId="233" toId="43">
</dataflow>
<dataflow id="280" from="j" to="j_6" fromId="41" toId="44">
</dataflow>
<dataflow id="281" from="StgValue_238" to="j_6" fromId="238" toId="44">
</dataflow>
<dataflow id="282" from="exitcond5" to="StgValue_45" fromId="42" toId="45">
</dataflow>
<dataflow id="283" from="j" to="tmp_187" fromId="41" toId="46">
</dataflow>
<dataflow id="284" from="StgValue_242" to="tmp_187" fromId="242" toId="46">
</dataflow>
<dataflow id="285" from="_ssdm_op_BitConcatenate.i7.i3.i1.i3" to="Lo_assign_1" fromId="257" toId="47">
</dataflow>
<dataflow id="286" from="j" to="Lo_assign_1" fromId="41" toId="47">
</dataflow>
<dataflow id="287" from="StgValue_252" to="Lo_assign_1" fromId="252" toId="47">
</dataflow>
<dataflow id="288" from="j" to="Lo_assign_1" fromId="41" toId="47">
</dataflow>
<dataflow id="289" from="StgValue_263" to="tmp_188" fromId="263" toId="48">
</dataflow>
<dataflow id="290" from="Lo_assign_1" to="tmp_188" fromId="47" toId="48">
</dataflow>
<dataflow id="291" from="tmp_187" to="Uj" fromId="46" toId="49">
</dataflow>
<dataflow id="292" from="StgValue_266" to="Uj" fromId="266" toId="49">
</dataflow>
<dataflow id="293" from="tmp_188" to="Uj" fromId="48" toId="49">
</dataflow>
<dataflow id="294" from="j" to="tmp_189_cast" fromId="41" toId="50">
</dataflow>
<dataflow id="295" from="tmp_292" to="tmp_293" fromId="35" toId="51">
</dataflow>
<dataflow id="296" from="tmp_189_cast" to="tmp_293" fromId="50" toId="51">
</dataflow>
<dataflow id="297" from="Lo_assign" to="tmp_358" fromId="36" toId="52">
</dataflow>
<dataflow id="298" from="Ui_2" to="tmp_358" fromId="38" toId="52">
</dataflow>
<dataflow id="300" from="llvm.part.select.i94" to="tmp_359" fromId="299" toId="53">
</dataflow>
<dataflow id="301" from="a_V_cast" to="tmp_359" fromId="20" toId="53">
</dataflow>
<dataflow id="303" from="StgValue_302" to="tmp_359" fromId="302" toId="53">
</dataflow>
<dataflow id="305" from="StgValue_304" to="tmp_359" fromId="304" toId="53">
</dataflow>
<dataflow id="306" from="Lo_assign" to="tmp_360" fromId="36" toId="54">
</dataflow>
<dataflow id="307" from="Ui_2" to="tmp_360" fromId="38" toId="54">
</dataflow>
<dataflow id="308" from="StgValue_266" to="tmp_361" fromId="266" toId="55">
</dataflow>
<dataflow id="309" from="Lo_assign" to="tmp_361" fromId="36" toId="55">
</dataflow>
<dataflow id="310" from="Ui_2" to="tmp_362" fromId="38" toId="56">
</dataflow>
<dataflow id="311" from="Lo_assign" to="tmp_362" fromId="36" toId="56">
</dataflow>
<dataflow id="312" from="tmp_358" to="tmp_363" fromId="52" toId="57">
</dataflow>
<dataflow id="313" from="tmp_360" to="tmp_363" fromId="54" toId="57">
</dataflow>
<dataflow id="314" from="tmp_362" to="tmp_363" fromId="56" toId="57">
</dataflow>
<dataflow id="315" from="tmp_358" to="tmp_364" fromId="52" toId="58">
</dataflow>
<dataflow id="316" from="tmp_359" to="tmp_364" fromId="53" toId="58">
</dataflow>
<dataflow id="317" from="a_V_cast" to="tmp_364" fromId="20" toId="58">
</dataflow>
<dataflow id="318" from="tmp_358" to="tmp_365" fromId="52" toId="59">
</dataflow>
<dataflow id="319" from="tmp_361" to="tmp_365" fromId="55" toId="59">
</dataflow>
<dataflow id="320" from="Lo_assign" to="tmp_365" fromId="36" toId="59">
</dataflow>
<dataflow id="321" from="StgValue_266" to="tmp_366" fromId="266" toId="60">
</dataflow>
<dataflow id="322" from="tmp_363" to="tmp_366" fromId="57" toId="60">
</dataflow>
<dataflow id="323" from="tmp_365" to="tmp_367" fromId="59" toId="61">
</dataflow>
<dataflow id="324" from="tmp_366" to="tmp_368" fromId="60" toId="62">
</dataflow>
<dataflow id="325" from="tmp_364" to="tmp_369" fromId="58" toId="63">
</dataflow>
<dataflow id="326" from="tmp_367" to="tmp_369" fromId="61" toId="63">
</dataflow>
<dataflow id="328" from="StgValue_327" to="tmp_370" fromId="327" toId="64">
</dataflow>
<dataflow id="329" from="tmp_368" to="tmp_370" fromId="62" toId="64">
</dataflow>
<dataflow id="330" from="tmp_369" to="p_Result_16" fromId="63" toId="65">
</dataflow>
<dataflow id="331" from="tmp_370" to="p_Result_16" fromId="64" toId="65">
</dataflow>
<dataflow id="332" from="p_Result_16" to="tmp_385" fromId="65" toId="66">
</dataflow>
<dataflow id="333" from="Lo_assign_1" to="tmp_372" fromId="47" toId="68">
</dataflow>
<dataflow id="334" from="Uj" to="tmp_372" fromId="49" toId="68">
</dataflow>
<dataflow id="335" from="Lo_assign_1" to="tmp_373" fromId="47" toId="69">
</dataflow>
<dataflow id="336" from="Uj" to="tmp_373" fromId="49" toId="69">
</dataflow>
<dataflow id="337" from="StgValue_266" to="tmp_374" fromId="266" toId="70">
</dataflow>
<dataflow id="338" from="Lo_assign_1" to="tmp_374" fromId="47" toId="70">
</dataflow>
<dataflow id="339" from="Uj" to="tmp_375" fromId="49" toId="71">
</dataflow>
<dataflow id="340" from="Lo_assign_1" to="tmp_375" fromId="47" toId="71">
</dataflow>
<dataflow id="341" from="tmp_372" to="tmp_376" fromId="68" toId="72">
</dataflow>
<dataflow id="342" from="tmp_373" to="tmp_376" fromId="69" toId="72">
</dataflow>
<dataflow id="343" from="tmp_375" to="tmp_376" fromId="71" toId="72">
</dataflow>
<dataflow id="344" from="tmp_372" to="tmp_377" fromId="68" toId="73">
</dataflow>
<dataflow id="346" from="StgValue_345" to="tmp_377" fromId="345" toId="73">
</dataflow>
<dataflow id="348" from="StgValue_347" to="tmp_377" fromId="347" toId="73">
</dataflow>
<dataflow id="349" from="tmp_372" to="tmp_378" fromId="68" toId="74">
</dataflow>
<dataflow id="350" from="tmp_374" to="tmp_378" fromId="70" toId="74">
</dataflow>
<dataflow id="351" from="Lo_assign_1" to="tmp_378" fromId="47" toId="74">
</dataflow>
<dataflow id="352" from="StgValue_266" to="tmp_379" fromId="266" toId="75">
</dataflow>
<dataflow id="353" from="tmp_376" to="tmp_379" fromId="72" toId="75">
</dataflow>
<dataflow id="354" from="tmp_378" to="tmp_380" fromId="74" toId="76">
</dataflow>
<dataflow id="355" from="tmp_379" to="tmp_381" fromId="75" toId="77">
</dataflow>
<dataflow id="356" from="tmp_377" to="tmp_382" fromId="73" toId="78">
</dataflow>
<dataflow id="357" from="tmp_380" to="tmp_382" fromId="76" toId="78">
</dataflow>
<dataflow id="358" from="StgValue_327" to="tmp_383" fromId="327" toId="79">
</dataflow>
<dataflow id="359" from="tmp_381" to="tmp_383" fromId="77" toId="79">
</dataflow>
<dataflow id="360" from="tmp_382" to="p_Result_17" fromId="78" toId="80">
</dataflow>
<dataflow id="361" from="tmp_383" to="p_Result_17" fromId="79" toId="80">
</dataflow>
<dataflow id="362" from="p_Result_17" to="tmp_386" fromId="80" toId="81">
</dataflow>
<dataflow id="363" from="tmp_386" to="tmp_192" fromId="81" toId="82">
</dataflow>
<dataflow id="364" from="tmp_385" to="tmp_192" fromId="66" toId="82">
</dataflow>
<dataflow id="365" from="tmp_386" to="tmp_192" fromId="81" toId="83">
</dataflow>
<dataflow id="366" from="tmp_385" to="tmp_192" fromId="66" toId="83">
</dataflow>
<dataflow id="367" from="tmp_386" to="tmp_192" fromId="81" toId="84">
</dataflow>
<dataflow id="368" from="tmp_385" to="tmp_192" fromId="66" toId="84">
</dataflow>
<dataflow id="369" from="tmp_386" to="tmp_192" fromId="81" toId="85">
</dataflow>
<dataflow id="370" from="tmp_385" to="tmp_192" fromId="66" toId="85">
</dataflow>
<dataflow id="371" from="tmp_386" to="tmp_192" fromId="81" toId="86">
</dataflow>
<dataflow id="372" from="tmp_385" to="tmp_192" fromId="66" toId="86">
</dataflow>
<dataflow id="373" from="tmp_386" to="tmp_192" fromId="81" toId="87">
</dataflow>
<dataflow id="374" from="tmp_385" to="tmp_192" fromId="66" toId="87">
</dataflow>
<dataflow id="375" from="tmp_293" to="tmp_299_cast" fromId="51" toId="88">
</dataflow>
<dataflow id="376" from="pp_V" to="pp_V_addr_3" fromId="21" toId="89">
</dataflow>
<dataflow id="377" from="StgValue_219" to="pp_V_addr_3" fromId="219" toId="89">
</dataflow>
<dataflow id="378" from="tmp_299_cast" to="pp_V_addr_3" fromId="88" toId="89">
</dataflow>
<dataflow id="379" from="tmp_192" to="StgValue_90" fromId="87" toId="90">
</dataflow>
<dataflow id="380" from="pp_V_addr_3" to="StgValue_90" fromId="89" toId="90">
</dataflow>
<dataflow id="381" from="pp_V_addr" to="pp_V_load" fromId="22" toId="92">
</dataflow>
<dataflow id="382" from="pp_V_load" to="tmp" fromId="92" toId="93">
</dataflow>
<dataflow id="383" from="pps_V" to="pps_V_addr" fromId="23" toId="94">
</dataflow>
<dataflow id="384" from="StgValue_219" to="pps_V_addr" fromId="219" toId="94">
</dataflow>
<dataflow id="385" from="StgValue_219" to="pps_V_addr" fromId="219" toId="94">
</dataflow>
<dataflow id="386" from="tmp" to="StgValue_95" fromId="93" toId="95">
</dataflow>
<dataflow id="387" from="pps_V_addr" to="StgValue_95" fromId="94" toId="95">
</dataflow>
<dataflow id="389" from="StgValue_388" to="i_1" fromId="388" toId="97">
<condition id="102">
<or_exp><and_exp></and_exp></or_exp>
</condition>
</dataflow>
<dataflow id="390" from="StgValue_96" to="i_1" fromId="96" toId="97">
</dataflow>
<dataflow id="391" from="i_13" to="i_1" fromId="138" toId="97">
<BackEdge/>
<condition id="103">
<or_exp><and_exp><literal name="exitcond6" val="1"/>
</and_exp></or_exp>
</condition>
</dataflow>
<dataflow id="392" from="StgValue_139" to="i_1" fromId="139" toId="97">
<BackEdge/>
</dataflow>
<dataflow id="393" from="i_1" to="i_1_cast" fromId="97" toId="98">
</dataflow>
<dataflow id="394" from="i_1" to="exitcond4" fromId="97" toId="99">
</dataflow>
<dataflow id="396" from="StgValue_395" to="exitcond4" fromId="395" toId="99">
</dataflow>
<dataflow id="397" from="_ssdm_op_SpecLoopTripCount" to="empty_60" fromId="231" toId="100">
</dataflow>
<dataflow id="399" from="StgValue_398" to="empty_60" fromId="398" toId="100">
</dataflow>
<dataflow id="400" from="StgValue_398" to="empty_60" fromId="398" toId="100">
</dataflow>
<dataflow id="401" from="StgValue_398" to="empty_60" fromId="398" toId="100">
</dataflow>
<dataflow id="402" from="exitcond4" to="StgValue_101" fromId="99" toId="101">
</dataflow>
<dataflow id="403" from="i_1" to="tmp_185" fromId="97" toId="102">
</dataflow>
<dataflow id="405" from="StgValue_404" to="tmp_185" fromId="404" toId="102">
</dataflow>
<dataflow id="406" from="tmp_185" to="tmp_186" fromId="102" toId="103">
</dataflow>
<dataflow id="407" from="pps_V" to="pps_V_addr_5" fromId="23" toId="104">
</dataflow>
<dataflow id="408" from="StgValue_219" to="pps_V_addr_5" fromId="219" toId="104">
</dataflow>
<dataflow id="409" from="tmp_186" to="pps_V_addr_5" fromId="103" toId="104">
</dataflow>
<dataflow id="410" from="pps_V_addr_5" to="pps_V_load" fromId="104" toId="105">
</dataflow>
<dataflow id="411" from="i_1" to="tmp_184" fromId="97" toId="107">
</dataflow>
<dataflow id="412" from="pps_V_addr_5" to="pps_V_load" fromId="104" toId="108">
</dataflow>
<dataflow id="414" from="_ssdm_op_PartSelect.i31.i48.i32.i32" to="r_V" fromId="413" toId="109">
</dataflow>
<dataflow id="415" from="pps_V_load" to="r_V" fromId="108" toId="109">
</dataflow>
<dataflow id="417" from="StgValue_416" to="r_V" fromId="416" toId="109">
</dataflow>
<dataflow id="419" from="StgValue_418" to="r_V" fromId="418" toId="109">
</dataflow>
<dataflow id="420" from="r_V" to="r_V_8" fromId="109" toId="110">
</dataflow>
<dataflow id="421" from="pps_V" to="pps_V_addr_6" fromId="23" toId="111">
</dataflow>
<dataflow id="422" from="StgValue_219" to="pps_V_addr_6" fromId="219" toId="111">
</dataflow>
<dataflow id="423" from="tmp_184" to="pps_V_addr_6" fromId="107" toId="111">
</dataflow>
<dataflow id="424" from="r_V_8" to="StgValue_112" fromId="110" toId="112">
</dataflow>
<dataflow id="425" from="pps_V_addr_6" to="StgValue_112" fromId="111" toId="112">
</dataflow>
<dataflow id="426" from="StgValue_223" to="j_1" fromId="223" toId="114">
<condition id="104">
<or_exp><and_exp></and_exp></or_exp>
</condition>
</dataflow>
<dataflow id="427" from="StgValue_113" to="j_1" fromId="113" toId="114">
</dataflow>
<dataflow id="428" from="j_7" to="j_1" fromId="119" toId="114">
<BackEdge/>
<condition id="105">
<or_exp><and_exp></and_exp></or_exp>
</condition>
</dataflow>
<dataflow id="429" from="StgValue_146" to="j_1" fromId="146" toId="114">
<BackEdge/>
</dataflow>
<dataflow id="430" from="j_1" to="j_1_cast3" fromId="114" toId="115">
</dataflow>
<dataflow id="431" from="j_1" to="j_1_cast3_cast" fromId="114" toId="116">
</dataflow>
<dataflow id="432" from="j_1" to="exitcond6" fromId="114" toId="117">
</dataflow>
<dataflow id="433" from="StgValue_229" to="exitcond6" fromId="229" toId="117">
</dataflow>
<dataflow id="434" from="_ssdm_op_SpecLoopTripCount" to="empty_61" fromId="231" toId="118">
</dataflow>
<dataflow id="435" from="StgValue_233" to="empty_61" fromId="233" toId="118">
</dataflow>
<dataflow id="436" from="StgValue_233" to="empty_61" fromId="233" toId="118">
</dataflow>
<dataflow id="437" from="StgValue_233" to="empty_61" fromId="233" toId="118">
</dataflow>
<dataflow id="438" from="j_1" to="j_7" fromId="114" toId="119">
</dataflow>
<dataflow id="439" from="StgValue_238" to="j_7" fromId="238" toId="119">
</dataflow>
<dataflow id="440" from="exitcond6" to="StgValue_120" fromId="117" toId="120">
</dataflow>
<dataflow id="441" from="i_1" to="ult" fromId="97" toId="121">
</dataflow>
<dataflow id="442" from="j_1_cast3_cast" to="ult" fromId="116" toId="121">
</dataflow>
<dataflow id="443" from="ult" to="rev5" fromId="121" toId="122">
</dataflow>
<dataflow id="445" from="StgValue_444" to="rev5" fromId="444" toId="122">
</dataflow>
<dataflow id="446" from="i_1_cast" to="tmp_196" fromId="98" toId="123">
</dataflow>
<dataflow id="447" from="j_1_cast3" to="tmp_196" fromId="115" toId="123">
</dataflow>
<dataflow id="448" from="tmp_196" to="tmp_197" fromId="123" toId="124">
</dataflow>
<dataflow id="450" from="StgValue_449" to="tmp_197" fromId="449" toId="124">
</dataflow>
<dataflow id="451" from="rev5" to="or_cond" fromId="122" toId="125">
</dataflow>
<dataflow id="452" from="tmp_197" to="or_cond" fromId="124" toId="125">
</dataflow>
<dataflow id="453" from="or_cond" to="StgValue_126" fromId="125" toId="126">
</dataflow>
<dataflow id="454" from="tmp_196" to="tmp_198_cast" fromId="123" toId="127">
</dataflow>
<dataflow id="455" from="_ssdm_op_BitConcatenate.i6.i3.i3" to="tmp_294" fromId="244" toId="128">
</dataflow>
<dataflow id="456" from="j_1" to="tmp_294" fromId="114" toId="128">
</dataflow>
<dataflow id="457" from="StgValue_223" to="tmp_294" fromId="223" toId="128">
</dataflow>
<dataflow id="458" from="tmp_294" to="p_shl2_cast" fromId="128" toId="129">
</dataflow>
<dataflow id="459" from="_ssdm_op_BitConcatenate.i4.i3.i1" to="tmp_295" fromId="249" toId="130">
</dataflow>
<dataflow id="460" from="j_1" to="tmp_295" fromId="114" toId="130">
</dataflow>
<dataflow id="461" from="StgValue_252" to="tmp_295" fromId="252" toId="130">
</dataflow>
<dataflow id="462" from="tmp_295" to="p_shl3_cast" fromId="130" toId="131">
</dataflow>
<dataflow id="463" from="p_shl2_cast" to="tmp_296" fromId="129" toId="132">
</dataflow>
<dataflow id="464" from="p_shl3_cast" to="tmp_296" fromId="131" toId="132">
</dataflow>
<dataflow id="465" from="tmp_296" to="tmp_297" fromId="132" toId="133">
</dataflow>
<dataflow id="466" from="tmp_198_cast" to="tmp_297" fromId="127" toId="133">
</dataflow>
<dataflow id="467" from="tmp_297" to="tmp_303_cast" fromId="133" toId="134">
</dataflow>
<dataflow id="468" from="pp_V" to="pp_V_addr_4" fromId="21" toId="135">
</dataflow>
<dataflow id="469" from="StgValue_219" to="pp_V_addr_4" fromId="219" toId="135">
</dataflow>
<dataflow id="470" from="tmp_303_cast" to="pp_V_addr_4" fromId="134" toId="135">
</dataflow>
<dataflow id="471" from="pp_V_addr_4" to="pp_V_load_2" fromId="135" toId="136">
</dataflow>
<dataflow id="472" from="pps_V_addr_6" to="pps_V_load_4" fromId="111" toId="137">
</dataflow>
<dataflow id="473" from="i_1" to="i_13" fromId="97" toId="138">
</dataflow>
<dataflow id="474" from="StgValue_388" to="i_13" fromId="388" toId="138">
</dataflow>
<dataflow id="475" from="pp_V_addr_4" to="pp_V_load_2" fromId="135" toId="140">
</dataflow>
<dataflow id="476" from="pp_V_load_2" to="tmp_199" fromId="140" toId="141">
</dataflow>
<dataflow id="477" from="pps_V_addr_6" to="pps_V_load_4" fromId="111" toId="142">
</dataflow>
<dataflow id="478" from="tmp_199" to="tmp_200" fromId="141" toId="143">
</dataflow>
<dataflow id="479" from="pps_V_load_4" to="tmp_200" fromId="142" toId="143">
</dataflow>
<dataflow id="480" from="tmp_200" to="StgValue_144" fromId="143" toId="144">
</dataflow>
<dataflow id="481" from="pps_V_addr_6" to="StgValue_144" fromId="111" toId="144">
</dataflow>
<dataflow id="482" from="p_Result_s" to="p_Val2_34" fromId="182" toId="147">
<BackEdge/>
<condition id="106">
<or_exp><and_exp></and_exp></or_exp>
</condition>
</dataflow>
<dataflow id="483" from="StgValue_183" to="p_Val2_34" fromId="183" toId="147">
<BackEdge/>
</dataflow>
<dataflow id="485" from="StgValue_484" to="p_Val2_34" fromId="484" toId="147">
<condition id="107">
<or_exp><and_exp><literal name="exitcond4" val="1"/>
</and_exp></or_exp>
</condition>
</dataflow>
<dataflow id="486" from="StgValue_106" to="p_Val2_34" fromId="106" toId="147">
</dataflow>
<dataflow id="487" from="i_12" to="i_2" fromId="151" toId="148">
<BackEdge/>
<condition id="108">
<or_exp><and_exp></and_exp></or_exp>
</condition>
</dataflow>
<dataflow id="488" from="StgValue_183" to="i_2" fromId="183" toId="148">
<BackEdge/>
</dataflow>
<dataflow id="490" from="StgValue_489" to="i_2" fromId="489" toId="148">
<condition id="109">
<or_exp><and_exp><literal name="exitcond4" val="1"/>
</and_exp></or_exp>
</condition>
</dataflow>
<dataflow id="491" from="StgValue_106" to="i_2" fromId="106" toId="148">
</dataflow>
<dataflow id="492" from="i_2" to="exitcond" fromId="148" toId="149">
</dataflow>
<dataflow id="493" from="StgValue_395" to="exitcond" fromId="395" toId="149">
</dataflow>
<dataflow id="494" from="_ssdm_op_SpecLoopTripCount" to="empty_62" fromId="231" toId="150">
</dataflow>
<dataflow id="496" from="StgValue_495" to="empty_62" fromId="495" toId="150">
</dataflow>
<dataflow id="497" from="StgValue_495" to="empty_62" fromId="495" toId="150">
</dataflow>
<dataflow id="498" from="StgValue_495" to="empty_62" fromId="495" toId="150">
</dataflow>
<dataflow id="499" from="i_2" to="i_12" fromId="148" toId="151">
</dataflow>
<dataflow id="500" from="StgValue_388" to="i_12" fromId="388" toId="151">
</dataflow>
<dataflow id="501" from="exitcond" to="StgValue_152" fromId="149" toId="152">
</dataflow>
<dataflow id="503" from="_ssdm_op_BitConcatenate.i8.i4.i4" to="Li" fromId="502" toId="153">
</dataflow>
<dataflow id="504" from="i_2" to="Li" fromId="148" toId="153">
</dataflow>
<dataflow id="505" from="i_2" to="Li" fromId="148" toId="153">
</dataflow>
<dataflow id="507" from="StgValue_506" to="Ui" fromId="506" toId="154">
</dataflow>
<dataflow id="508" from="Li" to="Ui" fromId="153" toId="154">
</dataflow>
<dataflow id="509" from="Ui" to="tmp_193" fromId="154" toId="155">
</dataflow>
<dataflow id="511" from="StgValue_510" to="tmp_193" fromId="510" toId="155">
</dataflow>
<dataflow id="512" from="tmp_193" to="Hi_assign" fromId="155" toId="156">
</dataflow>
<dataflow id="513" from="StgValue_510" to="Hi_assign" fromId="510" toId="156">
</dataflow>
<dataflow id="514" from="Ui" to="Hi_assign" fromId="154" toId="156">
</dataflow>
<dataflow id="515" from="i_2" to="tmp_194" fromId="148" toId="157">
</dataflow>
<dataflow id="516" from="pps_V" to="pps_V_addr_7" fromId="23" toId="158">
</dataflow>
<dataflow id="517" from="StgValue_219" to="pps_V_addr_7" fromId="219" toId="158">
</dataflow>
<dataflow id="518" from="tmp_194" to="pps_V_addr_7" fromId="157" toId="158">
</dataflow>
<dataflow id="519" from="pps_V_addr_7" to="p_Val2_s" fromId="158" toId="159">
</dataflow>
<dataflow id="520" from="p_Val2_34" to="StgValue_160" fromId="147" toId="160">
</dataflow>
<dataflow id="521" from="pps_V_addr_7" to="p_Val2_s" fromId="158" toId="161">
</dataflow>
<dataflow id="522" from="p_Val2_s" to="tmp_387" fromId="161" toId="162">
</dataflow>
<dataflow id="523" from="tmp_387" to="loc_V" fromId="162" toId="163">
</dataflow>
<dataflow id="524" from="Li" to="tmp_388" fromId="153" toId="164">
</dataflow>
<dataflow id="525" from="Hi_assign" to="tmp_388" fromId="156" toId="164">
</dataflow>
<dataflow id="526" from="StgValue_510" to="tmp_389" fromId="510" toId="165">
</dataflow>
<dataflow id="527" from="Li" to="tmp_389" fromId="153" toId="165">
</dataflow>
<dataflow id="528" from="tmp_388" to="tmp_390" fromId="164" toId="166">
</dataflow>
<dataflow id="529" from="Li" to="tmp_390" fromId="153" toId="166">
</dataflow>
<dataflow id="530" from="Hi_assign" to="tmp_390" fromId="156" toId="166">
</dataflow>
<dataflow id="531" from="tmp_388" to="tmp_391" fromId="164" toId="167">
</dataflow>
<dataflow id="532" from="Hi_assign" to="tmp_391" fromId="156" toId="167">
</dataflow>
<dataflow id="533" from="Li" to="tmp_391" fromId="153" toId="167">
</dataflow>
<dataflow id="534" from="tmp_388" to="tmp_392" fromId="164" toId="168">
</dataflow>
<dataflow id="535" from="tmp_389" to="tmp_392" fromId="165" toId="168">
</dataflow>
<dataflow id="536" from="Li" to="tmp_392" fromId="153" toId="168">
</dataflow>
<dataflow id="537" from="StgValue_510" to="tmp_393" fromId="510" toId="169">
</dataflow>
<dataflow id="538" from="tmp_390" to="tmp_393" fromId="166" toId="169">
</dataflow>
<dataflow id="539" from="tmp_392" to="tmp_394" fromId="168" toId="170">
</dataflow>
<dataflow id="540" from="tmp_391" to="tmp_395" fromId="167" toId="171">
</dataflow>
<dataflow id="541" from="tmp_393" to="tmp_396" fromId="169" toId="172">
</dataflow>
<dataflow id="542" from="loc_V" to="tmp_397" fromId="163" toId="173">
</dataflow>
<dataflow id="543" from="tmp_394" to="tmp_397" fromId="170" toId="173">
</dataflow>
<dataflow id="545" from="llvm.part.select.i188" to="tmp_398" fromId="544" toId="174">
</dataflow>
<dataflow id="546" from="tmp_397" to="tmp_398" fromId="173" toId="174">
</dataflow>
<dataflow id="548" from="StgValue_547" to="tmp_398" fromId="547" toId="174">
</dataflow>
<dataflow id="549" from="StgValue_304" to="tmp_398" fromId="304" toId="174">
</dataflow>
<dataflow id="550" from="tmp_388" to="tmp_399" fromId="164" toId="175">
</dataflow>
<dataflow id="551" from="tmp_398" to="tmp_399" fromId="174" toId="175">
</dataflow>
<dataflow id="552" from="tmp_397" to="tmp_399" fromId="173" toId="175">
</dataflow>
<dataflow id="554" from="StgValue_553" to="tmp_400" fromId="553" toId="176">
</dataflow>
<dataflow id="555" from="tmp_395" to="tmp_400" fromId="171" toId="176">
</dataflow>
<dataflow id="556" from="StgValue_553" to="tmp_401" fromId="553" toId="177">
</dataflow>
<dataflow id="557" from="tmp_396" to="tmp_401" fromId="172" toId="177">
</dataflow>
<dataflow id="558" from="tmp_400" to="p_demorgan" fromId="176" toId="178">
</dataflow>
<dataflow id="559" from="tmp_401" to="p_demorgan" fromId="177" toId="178">
</dataflow>
<dataflow id="560" from="p_demorgan" to="tmp_402" fromId="178" toId="179">
</dataflow>
<dataflow id="561" from="StgValue_553" to="tmp_402" fromId="553" toId="179">
</dataflow>
<dataflow id="562" from="p_Val2_34" to="tmp_403" fromId="147" toId="180">
</dataflow>
<dataflow id="563" from="tmp_402" to="tmp_403" fromId="179" toId="180">
</dataflow>
<dataflow id="564" from="tmp_399" to="tmp_404" fromId="175" toId="181">
</dataflow>
<dataflow id="565" from="p_demorgan" to="tmp_404" fromId="178" toId="181">
</dataflow>
<dataflow id="566" from="tmp_403" to="p_Result_s" fromId="180" toId="182">
</dataflow>
<dataflow id="567" from="tmp_404" to="p_Result_s" fromId="181" toId="182">
</dataflow>
<dataflow id="568" from="exitcond3" to="StgValue_2" fromId="26" toId="2">
</dataflow>
<dataflow id="569" from="exitcond5" to="StgValue_3" fromId="42" toId="3">
</dataflow>
<dataflow id="570" from="exitcond4" to="StgValue_13" fromId="99" toId="13">
</dataflow>
<dataflow id="571" from="exitcond6" to="StgValue_15" fromId="117" toId="15">
</dataflow>
<dataflow id="572" from="or_cond" to="StgValue_15" fromId="125" toId="15">
</dataflow>
<dataflow id="573" from="or_cond" to="StgValue_16" fromId="125" toId="16">
</dataflow>
<dataflow id="574" from="exitcond" to="StgValue_17" fromId="149" toId="17">
</dataflow>
</dataflows>


</stg>
